<?xml version="1.0" encoding="utf-8"?>
<publishData>
  <publishProfile publishUrl="\\hughman\wwwroot\Gramps" deleteExistingFiles="True" ftpAnonymousLogin="False" ftpPassiveMode="True" msdeploySite="" msdeploySiteID="" msdeployRemoteSitePhysicalPath="" msdeployAllowUntrustedCertificate="False" msdeploySkipExtraFilesOnServer="True" msdeployMarkAsApp="False" profileName="Test" publishMethod="FileSystem" replaceMatchingFiles="False" userName="" savePWD="False" userPWD="" SelectedForPublish="False">
    <file relUrl="Views/Shared/CallNavigationButtons.ascx" publishTime="07/22/2011 07:26:03" />
    <file relUrl="Content/font/Cicle_Shadow-webfont.svg" publishTime="07/22/2011 07:25:59" />
    <file relUrl="Views/EmailsForCall/Edit.aspx" publishTime="07/22/2011 07:26:03" />
    <file relUrl="Content/Common/Icons/page_white_text.png" publishTime="07/22/2011 07:25:59" />
    <file relUrl="bin/NPOI.POIFS.xml" publishTime="07/22/2011 07:25:55" />
    <file relUrl="Scripts/tiny_mce/plugins/advlink/link.htm" publishTime="07/22/2011 07:26:00" />
    <file relUrl="Content/images/ui-bg_inset-hard_100_fcfdfd_1x100.png" publishTime="07/22/2011 07:25:59" />
    <file relUrl="Content/Common/Icons/Mvc/TabStrip.png" publishTime="07/22/2011 07:25:59" />
    <file relUrl="Scripts/jquery.jqEasyCharCounter.min.js" publishTime="07/22/2011 07:26:00" />
    <file relUrl="bin/NHibernate.Validator.dll" publishTime="07/22/2011 07:25:54" />
    <file relUrl="Scripts/tiny_mce/plugins/wordcount/editor_plugin.js" publishTime="07/22/2011 07:26:02" />
    <file relUrl="Scripts/tiny_mce/themes/advanced/editor_template.js" publishTime="07/22/2011 07:26:02" />
    <file relUrl="Content/Common/Icons/Suites_32/CMS.png" publishTime="07/22/2011 07:25:59" />
    <file relUrl="Scripts/tiny_mce/plugins/table/editor_plugin_src.js" publishTime="07/22/2011 07:26:02" />
    <file relUrl="AppReleaseSettings.config" publishTime="03/28/2011 14:38:23" />
    <file relUrl="Scripts/tiny_mce/plugins/advlink/langs/en_dlg.js" publishTime="07/22/2011 07:26:00" />
    <file relUrl="Scripts/tiny_mce/plugins/emotions/img/smiley-tongue-out.gif" publishTime="07/22/2011 07:26:00" />
    <file relUrl="Scripts/tiny_mce/plugins/xhtmlxtras/abbr.htm" publishTime="07/22/2011 07:26:02" />
    <file relUrl="Scripts/tiny_mce/plugins/safari/editor_plugin_src.js" publishTime="07/22/2011 07:26:02" />
    <file relUrl="Scripts/tiny_mce/themes/advanced/skins/o2k7/img/button_bg_black.png" publishTime="07/22/2011 07:26:02" />
    <file relUrl="Scripts/tiny_mce/plugins/nonbreaking/editor_plugin.js" publishTime="07/22/2011 07:26:02" />
    <file relUrl="Scripts/jquery.CaesMutioptionControl.js" publishTime="07/22/2011 07:26:00" />
    <file relUrl="Images/arrow_fat_up.gif" publishTime="07/22/2011 07:26:00" />
    <file relUrl="Scripts/tiny_mce/plugins/preview/jscripts/embed.js" publishTime="07/22/2011 07:26:02" />
    <file relUrl="Scripts/tiny_mce/plugins/autosave/editor_plugin.js" publishTime="07/22/2011 07:26:00" />
    <file relUrl="Scripts/tiny_mce/plugins/wordcount/editor_plugin_src.js" publishTime="07/22/2011 07:26:02" />
    <file relUrl="Scripts/tiny_mce/plugins/advhr/langs/en_dlg.js" publishTime="07/22/2011 07:26:00" />
    <file relUrl="Scripts/tiny_mce/plugins/example/langs/en_dlg.js" publishTime="07/22/2011 07:26:00" />
    <file relUrl="Views/Report/TemplateIndex.aspx" publishTime="07/22/2011 07:26:03" />
    <file relUrl="Scripts/tiny_mce/themes/advanced/js/source_editor.js" publishTime="07/22/2011 07:26:02" />
    <file relUrl="Content/Common/Icons/folder.png" publishTime="07/22/2011 07:25:59" />
    <file relUrl="Scripts/tiny_mce/themes/advanced/color_picker.htm" publishTime="07/22/2011 07:26:02" />
    <file relUrl="Content/images/ui-bg_gloss-wave_55_5c9ccc_500x100.png" publishTime="07/22/2011 07:25:59" />
    <file relUrl="Content/font/Cicle_Semi_Italic-webfont.ttf" publishTime="07/22/2011 07:25:59" />
    <file relUrl="Scripts/tiny_mce/plugins/preview/editor_plugin.js" publishTime="07/22/2011 07:26:02" />
    <file relUrl="Scripts/tiny_mce/plugins/table/css/row.css" publishTime="07/22/2011 07:26:02" />
    <file relUrl="Content/Common/Icons/Mvc/Grid.png" publishTime="07/22/2011 07:25:59" />
    <file relUrl="Scripts/tiny_mce/langs/en.js" publishTime="07/22/2011 07:26:00" />
    <file relUrl="Scripts/tiny_mce/plugins/visualchars/editor_plugin.js" publishTime="07/22/2011 07:26:02" />
    <file relUrl="Scripts/tiny_mce/utils/mctabs.js" publishTime="07/22/2011 07:26:03" />
    <file relUrl="Views/Home/LoggedOut.aspx" publishTime="07/22/2011 07:26:03" />
    <file relUrl="Scripts/tiny_mce/plugins/table/cell.htm" publishTime="07/22/2011 07:26:02" />
    <file relUrl="Content/Common/Icons/Suites_32/WPF.png" publishTime="07/22/2011 07:25:59" />
    <file relUrl="Scripts/tiny_mce/plugins/xhtmlxtras/css/attributes.css" publishTime="07/22/2011 07:26:02" />
    <file relUrl="Robots.txt" publishTime="07/22/2011 07:26:00" />
    <file relUrl="Scripts/tiny_mce/plugins/inlinepopups/editor_plugin_src.js" publishTime="07/22/2011 07:26:01" />
    <file relUrl="Scripts/tiny_mce/plugins/emotions/img/smiley-sealed.gif" publishTime="07/22/2011 07:26:00" />
    <file relUrl="Scripts/tiny_mce/themes/advanced/js/link.js" publishTime="07/22/2011 07:26:02" />
    <file relUrl="Scripts/tiny_mce/plugins/xhtmlxtras/attributes.htm" publishTime="07/22/2011 07:26:02" />
    <file relUrl="Content/Common/orm-comparison.png" publishTime="07/22/2011 07:25:59" />
    <file relUrl="Content/font/Cicle_Semi-webfont.woff" publishTime="07/22/2011 07:25:59" />
    <file relUrl="Scripts/tiny_mce/plugins/pagebreak/editor_plugin_src.js" publishTime="07/22/2011 07:26:02" />
    <file relUrl="Scripts/tiny_mce/plugins/contextmenu/editor_plugin.js" publishTime="07/22/2011 07:26:00" />
    <file relUrl="Scripts/tiny_mce/plugins/emotions/img/smiley-smile.gif" publishTime="07/22/2011 07:26:00" />
    <file relUrl="Views/Editor/CreateReviewer.aspx" publishTime="07/22/2011 07:26:03" />
    <file relUrl="Views/Home/Index.aspx" publishTime="07/22/2011 07:26:03" />
    <file relUrl="Views/Investigator/Edit.aspx" publishTime="07/22/2011 07:26:03" />
    <file relUrl="Scripts/tiny_mce/plugins/media/js/media.js" publishTime="07/22/2011 07:26:02" />
    <file relUrl="Scripts/tiny_mce/plugins/fullpage/editor_plugin_src.js" publishTime="07/22/2011 07:26:00" />
    <file relUrl="Scripts/tiny_mce/themes/simple/langs/en.js" publishTime="07/22/2011 07:26:02" />
    <file relUrl="Scripts/tiny_mce/plugins/nonbreaking/editor_plugin_src.js" publishTime="07/22/2011 07:26:02" />
    <file relUrl="bin/Rhino.Mocks.dll" publishTime="07/22/2011 07:25:55" />
    <file relUrl="Content/Common/Icons/Suites_32/PD.png" publishTime="07/22/2011 07:25:59" />
    <file relUrl="Content/images/ui-bg_glass_85_dfeffc_1x400.png" publishTime="07/22/2011 07:25:59" />
    <file relUrl="Scripts/tiny_mce/plugins/autosave/editor_plugin_src.js" publishTime="07/22/2011 07:26:00" />
    <file relUrl="Scripts/MicrosoftAjax.debug.js" publishTime="07/22/2011 07:26:00" />
    <file relUrl="Views/Home/About.aspx" publishTime="07/22/2011 07:26:03" />
    <file relUrl="Scripts/tiny_mce/plugins/fullscreen/editor_plugin.js" publishTime="07/22/2011 07:26:01" />
    <file relUrl="Images/CheckMark-1.png" publishTime="07/22/2011 07:26:00" />
    <file relUrl="Scripts/tiny_mce/plugins/fullpage/langs/en_dlg.js" publishTime="07/22/2011 07:26:01" />
    <file relUrl="Gramps.Publish.xml" publishTime="08/05/2011 07:35:12" />
    <file relUrl="Scripts/tiny_mce/plugins/table/row.htm" publishTime="07/22/2011 07:26:02" />
    <file relUrl="Scripts/xVal.jquery.validate.js" publishTime="07/22/2011 07:26:03" />
    <file relUrl="Scripts/tiny_mce/plugins/tabfocus/editor_plugin.js" publishTime="07/22/2011 07:26:02" />
    <file relUrl="Scripts/tiny_mce/plugins/safari/editor_plugin.js" publishTime="07/22/2011 07:26:02" />
    <file relUrl="Scripts/tiny_mce/plugins/example/dialog.htm" publishTime="07/22/2011 07:26:00" />
    <file relUrl="Scripts/tiny_mce/plugins/xhtmlxtras/js/ins.js" publishTime="07/22/2011 07:26:02" />
    <file relUrl="Scripts/jquery-1.4.1.min.js" publishTime="07/22/2011 07:26:00" />
    <file relUrl="Content/font/Cicle_Semi_Italic-webfont.woff" publishTime="07/22/2011 07:25:59" />
    <file relUrl="Content/images/ui-bg_glass_75_d0e5f5_1x400.png" publishTime="07/22/2011 07:25:59" />
    <file relUrl="Scripts/tiny_mce/plugins/example/editor_plugin_src.js" publishTime="07/22/2011 07:26:00" />
    <file relUrl="Scripts/tiny_mce/plugins/table/js/row.js" publishTime="07/22/2011 07:26:02" />
    <file relUrl="bin/FluentNHibernate.dll" publishTime="07/22/2011 07:25:54" />
    <file relUrl="Images/big_print.png" publishTime="07/22/2011 07:26:00" />
    <file relUrl="Scripts/MicrosoftMvcAjax.js" publishTime="07/22/2011 07:26:00" />
    <file relUrl="Content/Common/Icons/Suites/mvc.png" publishTime="07/22/2011 07:25:59" />
    <file relUrl="Scripts/tiny_mce/plugins/fullpage/css/fullpage.css" publishTime="07/22/2011 07:26:00" />
    <file relUrl="Scripts/tiny_mce/plugins/table/js/cell.js" publishTime="07/22/2011 07:26:02" />
    <file relUrl="Scripts/tiny_mce/plugins/style/editor_plugin_src.js" publishTime="07/22/2011 07:26:02" />
    <file relUrl="Views/Investigator/Create.aspx" publishTime="07/22/2011 07:26:03" />
    <file relUrl="Scripts/tiny_mce/themes/advanced/skins/default/content.css" publishTime="07/22/2011 07:26:02" />
    <file relUrl="Scripts/tiny_mce/plugins/emotions/emotions.htm" publishTime="07/22/2011 07:26:00" />
    <file relUrl="Scripts/tiny_mce/plugins/advimage/css/advimage.css" publishTime="07/22/2011 07:26:00" />
    <file relUrl="Views/Shared/SystemMessage.ascx" publishTime="07/22/2011 07:26:03" />
    <file relUrl="Scripts/tiny_mce/themes/advanced/image.htm" publishTime="07/22/2011 07:26:02" />
    <file relUrl="Scripts/tiny_mce/plugins/template/blank.htm" publishTime="07/22/2011 07:26:02" />
    <file relUrl="Images/Rocket_launch.png" publishTime="07/22/2011 07:26:00" />
    <file relUrl="Content/font/Cicle_Fina-webfont.woff" publishTime="07/22/2011 07:25:59" />
    <file relUrl="Content/Common/Icons/Suites_32/JustCode.png" publishTime="07/22/2011 07:25:59" />
    <file relUrl="Scripts/tiny_mce/plugins/media/img/shockwave.gif" publishTime="07/22/2011 07:26:02" />
    <file relUrl="Content/Common/Icons/Suites_32/TFS.png" publishTime="07/22/2011 07:25:59" />
    <file relUrl="bin/NPOI.HSSF.dll" publishTime="07/22/2011 07:25:55" />
    <file relUrl="Scripts/tiny_mce/plugins/xhtmlxtras/js/del.js" publishTime="07/22/2011 07:26:02" />
    <file relUrl="Scripts/tiny_mce/plugins/media/editor_plugin.js" publishTime="07/22/2011 07:26:01" />
    <file relUrl="Content/telerik.windows7.css" publishTime="07/22/2011 07:25:59" />
    <file relUrl="Views/Shared/PublicLogOnUserControl.ascx" publishTime="07/22/2011 07:26:03" />
    <file relUrl="Scripts/tiny_mce/plugins/media/img/windowsmedia.gif" publishTime="07/22/2011 07:26:02" />
    <file relUrl="Scripts/tiny_mce/plugins/layer/editor_plugin.js" publishTime="07/22/2011 07:26:01" />
    <file relUrl="Scripts/jquery.bt.min.js" publishTime="07/22/2011 07:26:00" />
    <file relUrl="Views/EmailQueue/Edit.aspx" publishTime="07/22/2011 07:26:03" />
    <file relUrl="Scripts/jquery.validate-vsdoc.js" publishTime="07/22/2011 07:26:00" />
    <file relUrl="Views/Template/Edit.aspx" publishTime="07/22/2011 07:26:03" />
    <file relUrl="Views/Report/ReportPropertyColumns.ascx" publishTime="07/22/2011 07:26:03" />
    <file relUrl="Content/jquery-ui-1.8.4.custom.css" publishTime="07/22/2011 07:25:59" />
    <file relUrl="bin/Castle.Core.dll" publishTime="07/22/2011 07:25:53" />
    <file relUrl="Views/Proposal/ProposalAnswerDetails.ascx" publishTime="07/22/2011 07:26:03" />
    <file relUrl="Views/Editor/EditReviewer.aspx" publishTime="07/22/2011 07:26:03" />
    <file relUrl="Scripts/tiny_mce/plugins/preview/example.html" publishTime="07/22/2011 07:26:02" />
    <file relUrl="Content/images/ui-bg_glass_75.png" publishTime="07/22/2011 07:25:59" />
    <file relUrl="Content/Windows7/loading.gif" publishTime="07/22/2011 07:25:59" />
    <file relUrl="bin/MvcContrib.dll" publishTime="07/22/2011 07:25:54" />
    <file relUrl="Scripts/tiny_mce/plugins/advhr/rule.htm" publishTime="07/22/2011 07:26:00" />
    <file relUrl="Scripts/tiny_mce/plugins/fullpage/js/fullpage.js" publishTime="07/22/2011 07:26:01" />
    <file relUrl="Views/EmailQueue/Details.aspx" publishTime="07/22/2011 07:26:03" />
    <file relUrl="Scripts/tiny_mce/plugins/pagebreak/img/pagebreak.gif" publishTime="07/22/2011 07:26:02" />
    <file relUrl="Scripts/tiny_mce/plugins/iespell/editor_plugin_src.js" publishTime="07/22/2011 07:26:01" />
    <file relUrl="Scripts/tiny_mce/plugins/searchreplace/searchreplace.htm" publishTime="07/22/2011 07:26:02" />
    <file relUrl="Scripts/tiny_mce/plugins/spellchecker/editor_plugin.js" publishTime="07/22/2011 07:26:02" />
    <file relUrl="Scripts/tiny_mce/plugins/example/js/dialog.js" publishTime="07/22/2011 07:26:00" />
    <file relUrl="Content/Common/Icons/Mvc/PanelBar.png" publishTime="07/22/2011 07:25:59" />
    <file relUrl="Scripts/tiny_mce/plugins/spellchecker/css/content.css" publishTime="07/22/2011 07:26:02" />
    <file relUrl="Views/Question/SharedQuestionSetup.ascx" publishTime="07/22/2011 07:26:03" />
    <file relUrl="bin/Gramps.dll" publishTime="08/10/2011 08:32:50" />
    <file relUrl="Scripts/tiny_mce/plugins/save/editor_plugin.js" publishTime="07/22/2011 07:26:02" />
    <file relUrl="bin/NPOI.HPSF.dll" publishTime="07/22/2011 07:25:55" />
    <file relUrl="Content/font/Cicle_Semi-webfont.svg" publishTime="07/22/2011 07:25:59" />
    <file relUrl="Scripts/tiny_mce/plugins/inlinepopups/skins/clearlooks2/img/vertical.gif" publishTime="07/22/2011 07:26:01" />
    <file relUrl="Scripts/tiny_mce/plugins/style/css/props.css" publishTime="07/22/2011 07:26:02" />
    <file relUrl="Scripts/tiny_mce/plugins/xhtmlxtras/editor_plugin.js" publishTime="07/22/2011 07:26:02" />
    <file relUrl="Content/telerik.vista.css" publishTime="07/22/2011 07:25:59" />
    <file relUrl="Scripts/tiny_mce/plugins/template/langs/en_dlg.js" publishTime="07/22/2011 07:26:02" />
    <file relUrl="Views/Report/EditForCall.aspx" publishTime="07/22/2011 07:26:03" />
    <file relUrl="Scripts/tiny_mce/themes/advanced/skins/default/img/buttons.png" publishTime="07/22/2011 07:26:02" />
    <file relUrl="Content/Common/Icons/Ajax/Scheduler.png" publishTime="07/22/2011 07:25:59" />
    <file relUrl="Content/images/ui-bg_flat_55_fbec88_40x100.png" publishTime="07/22/2011 07:25:59" />
    <file relUrl="Scripts/tiny_mce/plugins/xhtmlxtras/ins.htm" publishTime="07/22/2011 07:26:02" />
    <file relUrl="Scripts/tiny_mce/tiny_mce_src.js" publishTime="07/22/2011 07:26:03" />
    <file relUrl="Scripts/tiny_mce/themes/advanced/skins/o2k7/content.css" publishTime="07/22/2011 07:26:02" />
    <file relUrl="Views/Public/ForgotPassword.aspx" publishTime="07/22/2011 07:26:03" />
    <file relUrl="Scripts/tiny_mce/plugins/xhtmlxtras/js/element_common.js" publishTime="07/22/2011 07:26:02" />
    <file relUrl="Views/EmailQueue/Index.aspx" publishTime="07/22/2011 07:26:03" />
    <file relUrl="Scripts/tiny_mce/plugins/style/langs/en_dlg.js" publishTime="07/22/2011 07:26:02" />
    <file relUrl="Scripts/tiny_mce/plugins/xhtmlxtras/del.htm" publishTime="07/22/2011 07:26:02" />
    <file relUrl="Images/arrow_fat_down.gif" publishTime="07/22/2011 07:26:00" />
    <file relUrl="Scripts/RenameForArray.js" publishTime="07/22/2011 07:26:00" />
    <file relUrl="bin/NPOI.HPSF.xml" publishTime="07/22/2011 07:25:55" />
    <file relUrl="Scripts/tiny_mce/plugins/emotions/langs/en_dlg.js" publishTime="07/22/2011 07:26:00" />
    <file relUrl="favicon.ico" publishTime="07/22/2011 07:26:03" />
    <file relUrl="Content/Common/Icons/Mvc/Menu.png" publishTime="07/22/2011 07:25:59" />
    <file relUrl="Scripts/tiny_mce/plugins/autoresize/editor_plugin_src.js" publishTime="07/22/2011 07:26:00" />
    <file relUrl="Scripts/tiny_mce/plugins/media/img/trans.gif" publishTime="07/22/2011 07:26:02" />
    <file relUrl="bin/NHibernate.dll" publishTime="07/22/2011 07:25:54" />
    <file relUrl="Scripts/tiny_mce/plugins/advhr/editor_plugin.js" publishTime="07/22/2011 07:26:00" />
    <file relUrl="Scripts/tiny_mce/themes/advanced/skins/default/img/tabs.gif" publishTime="07/22/2011 07:26:02" />
    <file relUrl="Scripts/tiny_mce/plugins/fullpage/fullpage.htm" publishTime="07/22/2011 07:26:00" />
    <file relUrl="Views/Editor/SendCall.aspx" publishTime="07/22/2011 07:26:03" />
    <file relUrl="Scripts/tiny_mce/plugins/emotions/img/smiley-wink.gif" publishTime="07/22/2011 07:26:00" />
    <file relUrl="Scripts/tiny_mce/plugins/searchreplace/css/searchreplace.css" publishTime="07/22/2011 07:26:02" />
    <file relUrl="Scripts/tiny_mce/plugins/paste/editor_plugin.js" publishTime="07/22/2011 07:26:02" />
    <file relUrl="Scripts/tiny_mce/themes/advanced/js/image.js" publishTime="07/22/2011 07:26:02" />
    <file relUrl="bin/Spring.Core.dll" publishTime="07/22/2011 07:25:55" />
    <file relUrl="Scripts/tiny_mce/plugins/iespell/editor_plugin.js" publishTime="07/22/2011 07:26:01" />
    <file relUrl="bin/Iesi.Collections.dll" publishTime="07/22/2011 07:25:54" />
    <file relUrl="bin/Castle.Windsor.dll" publishTime="07/22/2011 07:25:53" />
    <file relUrl="Views/Account/LogOn.aspx" publishTime="07/22/2011 07:26:03" />
    <file relUrl="bin/Microsoft.ReportViewer.WebForms.dll" publishTime="07/22/2011 07:25:54" />
    <file relUrl="Scripts/tiny_mce/plugins/table/css/table.css" publishTime="07/22/2011 07:26:02" />
    <file relUrl="Images/Page_excel.png" publishTime="07/22/2011 07:26:00" />
    <file relUrl="Scripts/tiny_mce/plugins/inlinepopups/skins/clearlooks2/window.css" publishTime="07/22/2011 07:26:01" />
    <file relUrl="Scripts/tiny_mce/plugins/advlink/editor_plugin.js" publishTime="07/22/2011 07:26:00" />
    <file relUrl="Scripts/tiny_mce/plugins/bbcode/editor_plugin.js" publishTime="07/22/2011 07:26:00" />
    <file relUrl="Scripts/tiny_mce/plugins/paste/pasteword.htm" publishTime="07/22/2011 07:26:02" />
    <file relUrl="bin/MvcContrib.Castle.dll" publishTime="07/22/2011 07:25:54" />
    <file relUrl="Content/font/Cicle_Semi-webfont.eot" publishTime="07/22/2011 07:25:59" />
    <file relUrl="Scripts/tiny_mce/plugins/media/img/realmedia.gif" publishTime="07/22/2011 07:26:02" />
    <file relUrl="Scripts/tiny_mce/themes/advanced/skins/o2k7/ui_silver.css" publishTime="07/22/2011 07:26:02" />
    <file relUrl="Scripts/tiny_mce/license.txt" publishTime="07/22/2011 07:26:00" />
    <file relUrl="Content/Common/Icons/Suites_32/WinForms.png" publishTime="07/22/2011 07:25:59" />
    <file relUrl="Scripts/tiny_mce/plugins/emotions/img/smiley-cry.gif" publishTime="07/22/2011 07:26:00" />
    <file relUrl="Scripts/jquery.enableTinyMce.js" publishTime="07/22/2011 07:26:00" />
    <file relUrl="Views/Proposal/AdminEdit.aspx" publishTime="08/05/2011 07:35:12" />
    <file relUrl="Content/Common/Icons/Sl/Chart.gif" publishTime="07/22/2011 07:25:59" />
    <file relUrl="Global.asax" publishTime="07/22/2011 07:26:00" />
    <file relUrl="Scripts/tiny_mce/themes/advanced/charmap.htm" publishTime="07/22/2011 07:26:02" />
    <file relUrl="Scripts/tiny_mce/plugins/print/editor_plugin_src.js" publishTime="07/22/2011 07:26:02" />
    <file relUrl="Scripts/tiny_mce/plugins/insertdatetime/editor_plugin_src.js" publishTime="07/22/2011 07:26:01" />
    <file relUrl="Scripts/tiny_mce/themes/advanced/skins/o2k7/ui_black.css" publishTime="07/22/2011 07:26:02" />
    <file relUrl="Scripts/tiny_mce/themes/simple/editor_template_src.js" publishTime="07/22/2011 07:26:02" />
    <file relUrl="Scripts/tiny_mce/themes/advanced/about.htm" publishTime="07/22/2011 07:26:02" />
    <file relUrl="bin/NPOI.Util.xml" publishTime="07/22/2011 07:25:55" />
    <file relUrl="Scripts/tiny_mce/plugins/advimage/langs/en_dlg.js" publishTime="07/22/2011 07:26:00" />
    <file relUrl="Views/Web.config" publishTime="07/22/2011 07:26:03" />
    <file relUrl="Images/CheckMark.png" publishTime="07/22/2011 07:26:00" />
    <file relUrl="Views/CallForProposal/Create.aspx" publishTime="07/22/2011 07:26:03" />
    <file relUrl="Scripts/tiny_mce/plugins/emotions/img/smiley-surprised.gif" publishTime="07/22/2011 07:26:00" />
    <file relUrl="Content/images/ui-icons_217bc0_256x240.png" publishTime="07/22/2011 07:25:59" />
    <file relUrl="bin/Gramps.pdb" publishTime="08/10/2011 08:32:50" />
    <file relUrl="Views/Template/Create.aspx" publishTime="07/22/2011 07:26:03" />
    <file relUrl="Views/Report/ReportFormForTemplate.ascx" publishTime="08/05/2011 07:35:13" />
    <file relUrl="Scripts/tiny_mce/plugins/xhtmlxtras/js/acronym.js" publishTime="07/22/2011 07:26:02" />
    <file relUrl="Scripts/tiny_mce/themes/advanced/skins/o2k7/img/button_bg_silver.png" publishTime="07/22/2011 07:26:02" />
    <file relUrl="Views/Question/Create.aspx" publishTime="07/22/2011 07:26:03" />
    <file relUrl="Scripts/tiny_mce/plugins/directionality/editor_plugin.js" publishTime="07/22/2011 07:26:00" />
    <file relUrl="Content/Common/Icons/edit.png" publishTime="07/22/2011 07:25:59" />
    <file relUrl="Images/cancled_transparent.png" publishTime="07/22/2011 07:26:00" />
    <file relUrl="Scripts/tiny_mce/plugins/emotions/img/smiley-innocent.gif" publishTime="07/22/2011 07:26:00" />
    <file relUrl="Scripts/tiny_mce/plugins/advlink/css/advlink.css" publishTime="07/22/2011 07:26:00" />
    <file relUrl="bin/HibernatingRhinos.Profiler.Appender.dll" publishTime="07/22/2011 07:25:54" />
    <file relUrl="Content/Common/Icons/Suites/orm.png" publishTime="07/22/2011 07:25:59" />
    <file relUrl="Content/Common/Icons/Ajax/Grid.png" publishTime="07/22/2011 07:25:59" />
    <file relUrl="Content/font/Cicle_Gordita_Italic-webfont.svg" publishTime="07/22/2011 07:25:59" />
    <file relUrl="Scripts/tiny_mce/plugins/media/img/flv_player.swf" publishTime="07/22/2011 07:26:02" />
    <file relUrl="Content/font/Cicle_Gordita-webfont.woff" publishTime="07/22/2011 07:25:59" />
    <file relUrl="Views/Proposal/AdminDetails.aspx" publishTime="07/22/2011 07:26:03" />
    <file relUrl="Images/loading.gif" publishTime="07/22/2011 07:26:00" />
    <file relUrl="Scripts/tiny_mce/plugins/pagebreak/css/content.css" publishTime="07/22/2011 07:26:02" />
    <file relUrl="bin/NPOI.HSSF.xml" publishTime="07/22/2011 07:25:55" />
    <file relUrl="Scripts/tiny_mce/plugins/template/editor_plugin.js" publishTime="07/22/2011 07:26:02" />
    <file relUrl="Content/font/Cicle_Gordita_Italic-webfont.eot" publishTime="07/22/2011 07:25:59" />
    <file relUrl="Views/CallForProposal/Launch.aspx" publishTime="07/22/2011 07:26:03" />
    <file relUrl="Scripts/tiny_mce/themes/advanced/link.htm" publishTime="07/22/2011 07:26:02" />
    <file relUrl="Content/Site.css" publishTime="07/22/2011 07:25:59" />
    <file relUrl="Content/font/Cicle_Gordita-webfont.svg" publishTime="07/22/2011 07:25:59" />
    <file relUrl="Scripts/tiny_mce/plugins/xhtmlxtras/js/attributes.js" publishTime="07/22/2011 07:26:02" />
    <file relUrl="Content/Common/Icons/delete.png" publishTime="07/22/2011 07:25:59" />
    <file relUrl="Scripts/tiny_mce/plugins/spellchecker/editor_plugin_src.js" publishTime="07/22/2011 07:26:02" />
    <file relUrl="Scripts/tiny_mce/themes/advanced/js/about.js" publishTime="07/22/2011 07:26:02" />
    <file relUrl="Scripts/tiny_mce/plugins/style/js/props.js" publishTime="07/22/2011 07:26:02" />
    <file relUrl="Scripts/tiny_mce/plugins/emotions/img/smiley-yell.gif" publishTime="07/22/2011 07:26:00" />
    <file relUrl="Scripts/tiny_mce/plugins/template/editor_plugin_src.js" publishTime="07/22/2011 07:26:02" />
    <file relUrl="bin/Microsoft.ReportViewer.Common.dll" publishTime="07/22/2011 07:25:54" />
    <file relUrl="bin/Newtonsoft.Json.dll" publishTime="07/22/2011 07:25:55" />
    <file relUrl="Scripts/tiny_mce/plugins/emotions/editor_plugin.js" publishTime="07/22/2011 07:26:00" />
    <file relUrl="bin/Telerik.Web.Mvc.dll" publishTime="07/22/2011 07:25:56" />
    <file relUrl="Scripts/tiny_mce/plugins/tabfocus/editor_plugin_src.js" publishTime="07/22/2011 07:26:02" />
    <file relUrl="Content/font/Cicle_Gordita-webfont.ttf" publishTime="07/22/2011 07:25:59" />
    <file relUrl="bin/Common.Logging.dll" publishTime="07/22/2011 07:25:53" />
    <file relUrl="Content/NPOITemplate.xls" publishTime="07/22/2011 07:25:59" />
    <file relUrl="Views/EmailTemplate/Index.aspx" publishTime="07/22/2011 07:26:03" />
    <file relUrl="Scripts/tiny_mce/plugins/emotions/editor_plugin_src.js" publishTime="07/22/2011 07:26:00" />
    <file relUrl="Scripts/tiny_mce/plugins/table/langs/en_dlg.js" publishTime="07/22/2011 07:26:02" />
    <file relUrl="Content/images/ui-icons_cd0a0a_256x240.png" publishTime="07/22/2011 07:25:59" />
    <file relUrl="Views/Report/CreateForTemplate.aspx" publishTime="07/22/2011 07:26:03" />
    <file relUrl="Images/logo-caes.png" publishTime="07/22/2011 07:26:00" />
    <file relUrl="Scripts/tiny_mce/plugins/advhr/js/rule.js" publishTime="07/22/2011 07:26:00" />
    <file relUrl="Views/EmailsForCall/Create.aspx" publishTime="07/22/2011 07:26:03" />
    <file relUrl="Views/Editor/Index.aspx" publishTime="07/22/2011 07:26:03" />
    <file relUrl="Images/small_print.png" publishTime="07/22/2011 07:26:00" />
    <file relUrl="Content/font/Cicle_Gordita_Italic-webfont.ttf" publishTime="07/22/2011 07:25:59" />
    <file relUrl="Scripts/tiny_mce/themes/advanced/langs/en.js" publishTime="07/22/2011 07:26:02" />
    <file relUrl="bin/Gramps.Core.dll" publishTime="08/10/2011 08:32:46" />
    <file relUrl="Scripts/tiny_mce/plugins/xhtmlxtras/editor_plugin_src.js" publishTime="07/22/2011 07:26:02" />
    <file relUrl="Views/Proposal/Create.aspx" publishTime="07/22/2011 10:19:13" />
    <file relUrl="Views/Error/Index.aspx" publishTime="07/22/2011 07:26:03" />
    <file relUrl="Scripts/tiny_mce/plugins/inlinepopups/skins/clearlooks2/img/horizontal.gif" publishTime="07/22/2011 07:26:01" />
    <file relUrl="Scripts/tiny_mce/plugins/table/js/merge_cells.js" publishTime="07/22/2011 07:26:02" />
    <file relUrl="Content/Common/Icons/Suites_32/AJAX.png" publishTime="07/22/2011 07:25:59" />
    <file relUrl="Scripts/tiny_mce/themes/advanced/anchor.htm" publishTime="07/22/2011 07:26:02" />
    <file relUrl="Scripts/tiny_mce/plugins/fullscreen/fullscreen.htm" publishTime="07/22/2011 07:26:01" />
    <file relUrl="Views/Shared/NavigationButtons.ascx" publishTime="07/22/2011 07:26:03" />
    <file relUrl="Scripts/tiny_mce/plugins/style/editor_plugin.js" publishTime="07/22/2011 07:26:02" />
    <file relUrl="bin/UCDArch.dll" publishTime="07/22/2011 07:25:56" />
    <file relUrl="Scripts/tiny_mce/plugins/style/props.htm" publishTime="07/22/2011 07:26:02" />
    <file relUrl="bin/NPOI.DDF.xml" publishTime="07/22/2011 07:25:55" />
    <file relUrl="Scripts/tiny_mce/plugins/table/table.htm" publishTime="07/22/2011 07:26:02" />
    <file relUrl="Scripts/tiny_mce/plugins/autoresize/editor_plugin.js" publishTime="07/22/2011 07:26:00" />
    <file relUrl="Views/Question/Edit.aspx" publishTime="07/22/2011 07:26:03" />
    <file relUrl="Scripts/tiny_mce/themes/advanced/skins/o2k7/ui.css" publishTime="07/22/2011 07:26:02" />
    <file relUrl="Scripts/tiny_mce/plugins/searchreplace/langs/en_dlg.js" publishTime="07/22/2011 07:26:02" />
    <file relUrl="Scripts/tiny_mce/themes/simple/img/icons.gif" publishTime="07/22/2011 07:26:02" />
    <file relUrl="Content/jquery.bt.css" publishTime="07/22/2011 07:25:59" />
    <file relUrl="Scripts/tiny_mce/themes/advanced/editor_template_src.js" publishTime="07/22/2011 07:26:02" />
    <file relUrl="Scripts/tiny_mce/themes/simple/skins/o2k7/img/button_bg.png" publishTime="07/22/2011 07:26:02" />
    <file relUrl="Views/EmailTemplate/Edit.aspx" publishTime="07/22/2011 07:26:03" />
    <file relUrl="Scripts/tiny_mce/themes/simple/skins/o2k7/ui.css" publishTime="07/22/2011 07:26:02" />
    <file relUrl="bin/NHibernate.Linq.dll" publishTime="07/22/2011 07:25:54" />
    <file relUrl="Content/images/ui-bg_inset-hard_100_f5f8f9_1x100.png" publishTime="07/22/2011 07:25:59" />
    <file relUrl="Scripts/tiny_mce/plugins/template/css/template.css" publishTime="07/22/2011 07:26:02" />
    <file relUrl="Scripts/tiny_mce/plugins/inlinepopups/skins/clearlooks2/img/alert.gif" publishTime="07/22/2011 07:26:01" />
    <file relUrl="Scripts/tiny_mce/plugins/print/editor_plugin.js" publishTime="07/22/2011 07:26:02" />
    <file relUrl="Scripts/tiny_mce/themes/advanced/js/charmap.js" publishTime="07/22/2011 07:26:02" />
    <file relUrl="Views/Question/SharedQuestionFields.ascx" publishTime="07/22/2011 07:26:03" />
    <file relUrl="Scripts/tiny_mce/plugins/noneditable/editor_plugin.js" publishTime="07/22/2011 07:26:02" />
    <file relUrl="Content/Common/Icons/Suites_32/MVC.png" publishTime="07/22/2011 07:25:59" />
    <file relUrl="Scripts/tiny_mce/plugins/advimage/editor_plugin_src.js" publishTime="07/22/2011 07:26:00" />
    <file relUrl="Scripts/tiny_mce/plugins/media/editor_plugin_src.js" publishTime="07/22/2011 07:26:01" />
    <file relUrl="Views/EmailsForCall/Index.aspx" publishTime="07/22/2011 07:26:03" />
    <file relUrl="Content/font/Cicle_Fina_Italic-webfont.svg" publishTime="07/22/2011 07:25:59" />
    <file relUrl="Views/CallForProposal/Edit.aspx" publishTime="07/22/2011 07:26:03" />
    <file relUrl="Scripts/tiny_mce/tiny_mce.js" publishTime="07/22/2011 07:26:03" />
    <file relUrl="Content/font/Cicle_Fina-webfont.svg" publishTime="07/22/2011 07:25:59" />
    <file relUrl="bin/Spring.Aop.dll" publishTime="07/22/2011 07:25:55" />
    <file relUrl="Scripts/tiny_mce/tiny_mce_popup.js" publishTime="07/22/2011 07:26:03" />
    <file relUrl="Scripts/tiny_mce/themes/advanced/skins/default/dialog.css" publishTime="07/22/2011 07:26:02" />
    <file relUrl="bin/NPOI.dll" publishTime="07/22/2011 07:25:55" />
    <file relUrl="Scripts/tiny_mce/plugins/fullpage/editor_plugin.js" publishTime="07/22/2011 07:26:00" />
    <file relUrl="Content/font/Cicle_Semi_Italic-webfont.eot" publishTime="07/22/2011 07:25:59" />
    <file relUrl="bin/NPOI.DDF.dll" publishTime="07/22/2011 07:25:54" />
    <file relUrl="Content/Common/Icons/Sl/GridView.gif" publishTime="07/22/2011 07:25:59" />
    <file relUrl="Scripts/jquery.validate.js" publishTime="07/22/2011 07:26:00" />
    <file relUrl="bin/Microsoft.Web.Mvc.dll" publishTime="07/22/2011 07:25:54" />
    <file relUrl="Scripts/tiny_mce/plugins/media/css/content.css" publishTime="07/22/2011 07:26:01" />
    <file relUrl="Scripts/tiny_mce/plugins/emotions/img/smiley-kiss.gif" publishTime="07/22/2011 07:26:00" />
    <file relUrl="Scripts/tiny_mce/plugins/inlinepopups/skins/clearlooks2/img/confirm.gif" publishTime="07/22/2011 07:26:01" />
    <file relUrl="Scripts/tiny_mce/plugins/contextmenu/editor_plugin_src.js" publishTime="07/22/2011 07:26:00" />
    <file relUrl="bin/NPOI.POIFS.dll" publishTime="07/22/2011 07:25:55" />
    <file relUrl="Scripts/tiny_mce/plugins/advhr/css/advhr.css" publishTime="07/22/2011 07:26:00" />
    <file relUrl="Scripts/tiny_mce/plugins/paste/langs/en_dlg.js" publishTime="07/22/2011 07:26:02" />
    <file relUrl="Scripts/tiny_mce/plugins/example/langs/en.js" publishTime="07/22/2011 07:26:00" />
    <file relUrl="Scripts/tiny_mce/plugins/table/merge_cells.htm" publishTime="07/22/2011 07:26:02" />
    <file relUrl="Scripts/tiny_mce/plugins/table/js/table.js" publishTime="07/22/2011 07:26:02" />
    <file relUrl="Scripts/tiny_mce/plugins/inlinepopups/skins/clearlooks2/img/corners.gif" publishTime="07/22/2011 07:26:01" />
    <file relUrl="Content/images/ui-icons_d8e7f3_256x240.png" publishTime="07/22/2011 07:25:59" />
    <file relUrl="bin/log4net.dll" publishTime="07/22/2011 07:25:56" />
    <file relUrl="Views/Report/EditForTemplate.aspx" publishTime="07/22/2011 07:26:03" />
    <file relUrl="Views/Shared/LogOnUserControl.ascx" publishTime="07/22/2011 07:26:03" />
    <file relUrl="Content/font/Cicle_Fina_Italic-webfont.woff" publishTime="07/22/2011 07:25:59" />
    <file relUrl="Content/Common/Icons/Suites_32/SL.png" publishTime="07/22/2011 07:25:59" />
    <file relUrl="Views/Public/ChangePasswordSuccess.aspx" publishTime="07/22/2011 07:26:03" />
    <file relUrl="Scripts/tiny_mce/plugins/xhtmlxtras/js/cite.js" publishTime="07/22/2011 07:26:02" />
    <file relUrl="Scripts/tiny_mce/plugins/xhtmlxtras/css/popup.css" publishTime="07/22/2011 07:26:02" />
    <file relUrl="Views/EmailsForCall/SendCall.aspx" publishTime="07/22/2011 07:26:03" />
    <file relUrl="Views/Public/LogOn.aspx" publishTime="07/22/2011 07:26:03" />
    <file relUrl="Content/Common/Icons/Suites/rep.png" publishTime="07/22/2011 07:25:59" />
    <file relUrl="Scripts/MicrosoftMvcAjax.debug.js" publishTime="07/22/2011 07:26:00" />
    <file relUrl="Scripts/tiny_mce/themes/simple/skins/default/ui.css" publishTime="07/22/2011 07:26:02" />
    <file relUrl="packages.config" publishTime="07/22/2011 07:26:03" />
    <file relUrl="Views/Report/CreateForCall.aspx" publishTime="07/22/2011 07:26:03" />
    <file relUrl="Scripts/tiny_mce/themes/advanced/skins/default/img/items.gif" publishTime="07/22/2011 07:26:02" />
    <file relUrl="Scripts/tiny_mce/plugins/bbcode/editor_plugin_src.js" publishTime="07/22/2011 07:26:00" />
    <file relUrl="bin/Microsoft.Practices.ServiceLocation.dll" publishTime="07/22/2011 07:25:54" />
    <file relUrl="Images/plus.png" publishTime="07/22/2011 07:26:00" />
    <file relUrl="Content/font.css" publishTime="07/22/2011 07:25:59" />
    <file relUrl="Views/EmailsForCall/BulkCreate.aspx" publishTime="07/22/2011 07:26:03" />
    <file relUrl="Views/Report/CallIndex.aspx" publishTime="07/22/2011 07:26:03" />
    <file relUrl="Views/Proposal/Home.aspx" publishTime="07/22/2011 07:26:03" />
    <file relUrl="Content/font/Cicle_Semi_Italic-webfont.svg" publishTime="07/22/2011 07:25:59" />
    <file relUrl="Content/font/Cicle_Semi-webfont.ttf" publishTime="07/22/2011 07:25:59" />
    <file relUrl="Scripts/tiny_mce/plugins/searchreplace/editor_plugin_src.js" publishTime="07/22/2011 07:26:02" />
    <file relUrl="Scripts/tiny_mce/themes/advanced/skins/o2k7/dialog.css" publishTime="07/22/2011 07:26:02" />
    <file relUrl="Content/font/Cicle_Fina-webfont.ttf" publishTime="07/22/2011 07:25:59" />
    <file relUrl="Scripts/tiny_mce/plugins/media/img/flash.gif" publishTime="07/22/2011 07:26:01" />
    <file relUrl="Content/Common/Icons/Suites/sl.png" publishTime="07/22/2011 07:25:59" />
    <file relUrl="Scripts/tiny_mce/plugins/table/css/cell.css" publishTime="07/22/2011 07:26:02" />
    <file relUrl="Scripts/tiny_mce/themes/advanced/img/icons.gif" publishTime="07/22/2011 07:26:02" />
    <file relUrl="Scripts/tiny_mce/plugins/preview/preview.html" publishTime="07/22/2011 07:26:02" />
    <file relUrl="Images/logo.jpg" publishTime="07/22/2011 07:26:00" />
    <file relUrl="Scripts/tiny_mce/plugins/table/editor_plugin.js" publishTime="07/22/2011 07:26:02" />
    <file relUrl="Scripts/tiny_mce/plugins/save/editor_plugin_src.js" publishTime="07/22/2011 07:26:02" />
    <file relUrl="Content/images/ui-bg_glass_95_fef1ec_1x400.png" publishTime="07/22/2011 07:25:59" />
    <file relUrl="Scripts/tiny_mce/plugins/paste/js/pastetext.js" publishTime="07/22/2011 07:26:02" />
    <file relUrl="Scripts/tiny_mce/themes/simple/skins/default/content.css" publishTime="07/22/2011 07:26:02" />
    <file relUrl="AppTestSettings.config" publishTime="03/28/2011 14:38:23" />
    <file relUrl="Scripts/tiny_mce/plugins/emotions/img/smiley-cool.gif" publishTime="07/22/2011 07:26:00" />
    <file relUrl="Scripts/tiny_mce/plugins/media/langs/en_dlg.js" publishTime="07/22/2011 07:26:02" />
    <file relUrl="Images/Cancel-1.png" publishTime="07/22/2011 07:26:00" />
    <file relUrl="Scripts/tiny_mce/plugins/xhtmlxtras/acronym.htm" publishTime="07/22/2011 07:26:02" />
    <file relUrl="Scripts/tiny_mce/plugins/emotions/img/smiley-undecided.gif" publishTime="07/22/2011 07:26:00" />
    <file relUrl="Views/Shared/Error.aspx" publishTime="07/22/2011 07:26:03" />
    <file relUrl="Scripts/tiny_mce/plugins/example/img/example.gif" publishTime="07/22/2011 07:26:00" />
    <file relUrl="Content/images/ui-icons_2e83ff_256x240.png" publishTime="07/22/2011 07:25:59" />
    <file relUrl="Scripts/tiny_mce/plugins/media/css/media.css" publishTime="07/22/2011 07:26:01" />
    <file relUrl="Content/Common/Icons/Ajax/Editor.png" publishTime="07/22/2011 07:25:59" />
    <file relUrl="Views/Proposal/AdminIndex.aspx" publishTime="08/05/2011 07:35:13" />
    <file relUrl="Views/Template/Index.aspx" publishTime="07/22/2011 07:26:03" />
    <file relUrl="Content/font/Cicle_Fina_Italic-webfont.ttf" publishTime="07/22/2011 07:25:59" />
    <file relUrl="Content/Common/Icons/Suites_32/ORM.png" publishTime="07/22/2011 07:25:59" />
    <file relUrl="Views/Report/ReportFormForCall.ascx" publishTime="08/05/2011 07:35:13" />
    <file relUrl="Scripts/tiny_mce/plugins/inlinepopups/skins/clearlooks2/img/button.gif" publishTime="07/22/2011 07:26:01" />
    <file relUrl="Scripts/tiny_mce/plugins/pagebreak/img/trans.gif" publishTime="07/22/2011 07:26:02" />
    <file relUrl="bin/Recaptcha.pdb" publishTime="07/22/2011 07:25:55" />
    <file relUrl="Content/Common/Icons/Suites/test.png" publishTime="07/22/2011 07:25:59" />
    <file relUrl="Content/font/Cicle_Shadow-webfont.ttf" publishTime="07/22/2011 07:25:59" />
    <file relUrl="Scripts/tiny_mce/plugins/emotions/img/smiley-frown.gif" publishTime="07/22/2011 07:26:00" />
    <file relUrl="Content/telerik.common.css" publishTime="07/22/2011 07:25:59" />
    <file relUrl="Content/Common/sprite.png" publishTime="07/22/2011 07:25:59" />
    <file relUrl="Scripts/tiny_mce/themes/advanced/skins/default/img/progress.gif" publishTime="07/22/2011 07:26:02" />
    <file relUrl="Scripts/tiny_mce/themes/advanced/langs/en_dlg.js" publishTime="07/22/2011 07:26:02" />
    <file relUrl="Scripts/tiny_mce/plugins/safari/blank.htm" publishTime="07/22/2011 07:26:02" />
    <file relUrl="Content/Common/Icons/Suites/wpf.png" publishTime="07/22/2011 07:25:59" />
    <file relUrl="Scripts/tiny_mce/plugins/media/js/embed.js" publishTime="07/22/2011 07:26:02" />
    <file relUrl="Views/Question/SharedQuestionSample.ascx" publishTime="07/22/2011 07:26:03" />
    <file relUrl="Content/Vista/sprite.png" publishTime="07/22/2011 07:25:59" />
    <file relUrl="Scripts/tiny_mce/plugins/inlinepopups/template.htm" publishTime="07/22/2011 07:26:01" />
    <file relUrl="Scripts/tiny_mce/themes/advanced/skins/default/img/menu_check.gif" publishTime="07/22/2011 07:26:02" />
    <file relUrl="Views/Proposal/Edit.aspx" publishTime="08/05/2011 07:35:13" />
    <file relUrl="Scripts/tiny_mce/plugins/directionality/editor_plugin_src.js" publishTime="07/22/2011 07:26:00" />
    <file relUrl="Images/logo-ucdavis.png" publishTime="07/22/2011 07:26:00" />
    <file relUrl="Scripts/tiny_mce/plugins/inlinepopups/editor_plugin.js" publishTime="07/22/2011 07:26:01" />
    <file relUrl="Scripts/tiny_mce/plugins/inlinepopups/skins/clearlooks2/img/buttons.gif" publishTime="07/22/2011 07:26:01" />
    <file relUrl="Scripts/tiny_mce/plugins/paste/pastetext.htm" publishTime="07/22/2011 07:26:02" />
    <file relUrl="Content/font/Cicle_Gordita_Italic-webfont.woff" publishTime="07/22/2011 07:25:59" />
    <file relUrl="Content/Common/Icons/Suites_32/REP.png" publishTime="07/22/2011 07:25:59" />
    <file relUrl="Scripts/tiny_mce/utils/form_utils.js" publishTime="07/22/2011 07:26:03" />
    <file relUrl="bin/Castle.MicroKernel.dll" publishTime="07/22/2011 07:25:53" />
    <file relUrl="bin/Gramps.Core.pdb" publishTime="08/10/2011 08:32:46" />
    <file relUrl="Content/Common/Icons/Sl/Scheduler.gif" publishTime="07/22/2011 07:25:59" />
    <file relUrl="Scripts/tiny_mce/plugins/xhtmlxtras/cite.htm" publishTime="07/22/2011 07:26:02" />
    <file relUrl="bin/xVal.dll" publishTime="07/22/2011 07:25:56" />
    <file relUrl="Scripts/tiny_mce/plugins/advlink/editor_plugin_src.js" publishTime="07/22/2011 07:26:00" />
    <file relUrl="Scripts/tiny_mce/plugins/searchreplace/editor_plugin.js" publishTime="07/22/2011 07:26:02" />
    <file relUrl="Views/Question/Index.aspx" publishTime="07/22/2011 07:26:03" />
    <file relUrl="Views/CallForProposal/Index.aspx" publishTime="08/05/2011 07:35:12" />
    <file relUrl="Content/images/ui-icons_469bdd_256x240.png" publishTime="07/22/2011 07:25:59" />
    <file relUrl="Scripts/MicrosoftMvcValidation.js" publishTime="07/22/2011 07:26:00" />
    <file relUrl="bin/Microsoft.ReportViewer.WebForms.xml" publishTime="07/22/2011 07:25:54" />
    <file relUrl="Scripts/tiny_mce/plugins/emotions/img/smiley-money-mouth.gif" publishTime="07/22/2011 07:26:00" />
    <file relUrl="Scripts/tiny_mce/utils/editable_selects.js" publishTime="07/22/2011 07:26:03" />
    <file relUrl="Scripts/tiny_mce/plugins/layer/editor_plugin_src.js" publishTime="07/22/2011 07:26:01" />
    <file relUrl="bin/MvcContrib.FluentHtml.dll" publishTime="07/22/2011 07:25:54" />
    <file relUrl="Scripts/tiny_mce/themes/simple/editor_template.js" publishTime="07/22/2011 07:26:02" />
    <file relUrl="Scripts/tiny_mce/plugins/noneditable/editor_plugin_src.js" publishTime="07/22/2011 07:26:02" />
    <file relUrl="Scripts/tiny_mce/plugins/emotions/img/smiley-laughing.gif" publishTime="07/22/2011 07:26:00" />
    <file relUrl="Scripts/tiny_mce/themes/advanced/skins/default/ui.css" publishTime="07/22/2011 07:26:02" />
    <file relUrl="AppDebugSettings.config" publishTime="03/28/2011 14:38:23" />
    <file relUrl="bin/NPOI.Util.dll" publishTime="07/22/2011 07:25:55" />
    <file relUrl="Scripts/tiny_mce/themes/advanced/js/color_picker.js" publishTime="07/22/2011 07:26:02" />
    <file relUrl="bin/NHibernate.ByteCode.Spring.dll" publishTime="07/22/2011 07:25:54" />
    <file relUrl="Scripts/tiny_mce/plugins/advhr/editor_plugin_src.js" publishTime="07/22/2011 07:26:00" />
    <file relUrl="Views/Proposal/ReviewerIndex.aspx" publishTime="08/05/2011 07:35:13" />
    <file relUrl="bin/Castle.DynamicProxy2.dll" publishTime="07/22/2011 07:25:53" />
    <file relUrl="Views/Public/ChangePassword.aspx" publishTime="07/22/2011 07:26:03" />
    <file relUrl="Scripts/tiny_mce/plugins/template/template.htm" publishTime="07/22/2011 07:26:02" />
    <file relUrl="Scripts/tiny_mce/plugins/template/js/template.js" publishTime="07/22/2011 07:26:02" />
    <file relUrl="Content/images/ui-icons_6da8d5_256x240.png" publishTime="07/22/2011 07:25:59" />
    <file relUrl="Scripts/jquery.jqEasyCharCounter.js" publishTime="07/22/2011 07:26:00" />
    <file relUrl="Views/Investigator/InvestigatorForm.ascx" publishTime="07/22/2011 07:26:03" />
    <file relUrl="Scripts/tiny_mce/plugins/media/media.htm" publishTime="07/22/2011 07:26:02" />
    <file relUrl="Content/font/Cicle_Fina-webfont.eot" publishTime="07/22/2011 07:25:59" />
    <file relUrl="Views/Editor/AddEditor.aspx" publishTime="07/22/2011 07:26:03" />
    <file relUrl="Scripts/tiny_mce/plugins/visualchars/editor_plugin_src.js" publishTime="07/22/2011 07:26:02" />
    <file relUrl="Scripts/tiny_mce/plugins/advimage/image.htm" publishTime="07/22/2011 07:26:00" />
    <file relUrl="Content/images/ui-bg_flat_0_aaaaaa_40x100.png" publishTime="07/22/2011 07:25:59" />
    <file relUrl="Scripts/tiny_mce/themes/advanced/skins/o2k7/img/button_bg.png" publishTime="07/22/2011 07:26:02" />
    <file relUrl="Scripts/jquery-1.4.1.js" publishTime="07/22/2011 07:26:00" />
    <file relUrl="Scripts/tiny_mce/plugins/paste/editor_plugin_src.js" publishTime="07/22/2011 07:26:02" />
    <file relUrl="Views/Proposal/Details.aspx" publishTime="08/05/2011 07:35:13" />
    <file relUrl="Scripts/jquery.validate.min.js" publishTime="07/22/2011 07:26:00" />
    <file relUrl="Scripts/MicrosoftAjax.js" publishTime="07/22/2011 07:26:00" />
    <file relUrl="Images/branding.jpg" publishTime="07/22/2011 07:26:00" />
    <file relUrl="Content/main.css" publishTime="07/22/2011 07:25:59" />
    <file relUrl="Scripts/tiny_mce/plugins/emotions/js/emotions.js" publishTime="07/22/2011 07:26:00" />
    <file relUrl="Scripts/tiny_mce/plugins/emotions/img/smiley-foot-in-mouth.gif" publishTime="07/22/2011 07:26:00" />
    <file relUrl="Scripts/tiny_mce/plugins/paste/js/pasteword.js" publishTime="07/22/2011 07:26:02" />
    <file relUrl="Scripts/tiny_mce/themes/advanced/source_editor.htm" publishTime="07/22/2011 07:26:02" />
    <file relUrl="Scripts/jquery-1.4.1-vsdoc.js" publishTime="07/22/2011 07:26:00" />
    <file relUrl="Scripts/tiny_mce/themes/advanced/img/colorpicker.jpg" publishTime="07/22/2011 07:26:02" />
    <file relUrl="Content/font/Cicle_Fina_Italic-webfont.eot" publishTime="07/22/2011 07:25:59" />
    <file relUrl="Content/Windows7/sprite.png" publishTime="07/22/2011 07:25:59" />
    <file relUrl="Scripts/tiny_mce/plugins/preview/editor_plugin_src.js" publishTime="07/22/2011 07:26:02" />
    <file relUrl="Content/font/Cicle_Shadow-webfont.woff" publishTime="07/22/2011 07:25:59" />
    <file relUrl="Scripts/tiny_mce/plugins/xhtmlxtras/langs/en_dlg.js" publishTime="07/22/2011 07:26:02" />
    <file relUrl="Web.config" publishTime="08/10/2011 08:33:27" />
    <file relUrl="Images/Big_pdf.png" publishTime="07/22/2011 07:26:00" />
    <file relUrl="Scripts/MicrosoftMvcValidation.debug.js" publishTime="07/22/2011 07:26:00" />
    <file relUrl="Views/Proposal/AdminReviewerProposalDetails.ascx" publishTime="08/05/2011 07:35:13" />
    <file relUrl="Content/Common/Icons/Suites/sitefinity.png" publishTime="07/22/2011 07:25:59" />
    <file relUrl="Views/Proposal/ReviewerDetails.aspx" publishTime="07/22/2011 07:26:03" />
    <file relUrl="Scripts/tiny_mce/plugins/xhtmlxtras/js/abbr.js" publishTime="07/22/2011 07:26:02" />
    <file relUrl="Scripts/tiny_mce/themes/simple/skins/o2k7/content.css" publishTime="07/22/2011 07:26:02" />
    <file relUrl="bin/Elmah.dll" publishTime="07/22/2011 07:25:53" />
    <file relUrl="Scripts/tiny_mce/plugins/searchreplace/js/searchreplace.js" publishTime="07/22/2011 07:26:02" />
    <file relUrl="Scripts/tiny_mce/utils/validate.js" publishTime="07/22/2011 07:26:03" />
    <file relUrl="Images/Cancel.png" publishTime="07/22/2011 07:26:00" />
    <file relUrl="Scripts/tiny_mce/themes/advanced/skins/default/img/menu_arrow.gif" publishTime="07/22/2011 07:26:02" />
    <file relUrl="Scripts/tiny_mce/plugins/spellchecker/img/wline.gif" publishTime="07/22/2011 07:26:02" />
    <file relUrl="Views/Report/Launch.aspx" publishTime="07/22/2011 07:26:03" />
    <file relUrl="Content/Vista/loading.gif" publishTime="07/22/2011 07:25:59" />
    <file relUrl="Views/Proposal/Confirmation.aspx" publishTime="07/22/2011 07:26:03" />
    <file relUrl="Content/font/Cicle_Shadow-webfont.eot" publishTime="07/22/2011 07:25:59" />
    <file relUrl="Content/Common/Icons/Suites_32/Test.png" publishTime="07/22/2011 07:25:59" />
    <file relUrl="Content/anytimec.css" publishTime="07/22/2011 07:25:59" />
    <file relUrl="Scripts/tiny_mce/jquery.tinymce.js" publishTime="07/22/2011 07:26:00" />
    <file relUrl="Scripts/tiny_mce/plugins/advimage/js/image.js" publishTime="07/22/2011 07:26:00" />
    <file relUrl="Content/Common/Icons/Suites/ajax.png" publishTime="07/22/2011 07:25:59" />
    <file relUrl="Views/Shared/PublicSite.Master" publishTime="07/22/2011 07:26:03" />
    <file relUrl="Images/ajax-loader.gif" publishTime="07/22/2011 07:26:00" />
    <file relUrl="Scripts/tiny_mce/plugins/fullscreen/editor_plugin_src.js" publishTime="07/22/2011 07:26:01" />
    <file relUrl="bin/NPOI.xml" publishTime="07/22/2011 07:25:55" />
    <file relUrl="Scripts/tiny_mce/plugins/advlink/js/advlink.js" publishTime="07/22/2011 07:26:00" />
    <file relUrl="Content/images/ui-icons_f9bd01_256x240.png" publishTime="07/22/2011 07:25:59" />
    <file relUrl="Scripts/tiny_mce/plugins/emotions/img/smiley-embarassed.gif" publishTime="07/22/2011 07:26:00" />
    <file relUrl="Content/Common/Icons/Sl/Docking.gif" publishTime="07/22/2011 07:25:59" />
    <file relUrl="Content/Common/validation-error-message.png" publishTime="07/22/2011 07:25:59" />
    <file relUrl="Images/Details.png" publishTime="07/22/2011 07:26:00" />
    <file relUrl="Content/Common/Icons/Suites/win.png" publishTime="07/22/2011 07:25:59" />
    <file relUrl="Scripts/tiny_mce/plugins/example/editor_plugin.js" publishTime="07/22/2011 07:26:00" />
    <file relUrl="Scripts/tiny_mce/plugins/advimage/img/sample.gif" publishTime="07/22/2011 07:26:00" />
    <file relUrl="Scripts/tiny_mce/plugins/pagebreak/editor_plugin.js" publishTime="07/22/2011 07:26:02" />
    <file relUrl="Scripts/tiny_mce/plugins/media/img/quicktime.gif" publishTime="07/22/2011 07:26:02" />
    <file relUrl="Views/Shared/Site.Master" publishTime="07/22/2011 07:26:03" />
    <file relUrl="Scripts/tiny_mce/plugins/insertdatetime/editor_plugin.js" publishTime="07/22/2011 07:26:01" />
    <file relUrl="Scripts/tiny_mce/plugins/advimage/editor_plugin.js" publishTime="07/22/2011 07:26:00" />
    <file relUrl="bin/Recaptcha.dll" publishTime="07/22/2011 07:25:55" />
    <file relUrl="Scripts/tiny_mce/themes/advanced/js/anchor.js" publishTime="07/22/2011 07:26:02" />
    <file relUrl="Content/font/Cicle_Gordita-webfont.eot" publishTime="07/22/2011 07:25:59" />
  </publishProfile>
  <publishProfile publishUrl="\\glurmo\wwwroot\Gramps" deleteExistingFiles="False" ftpAnonymousLogin="False" ftpPassiveMode="True" msdeploySite="" msdeploySiteID="" msdeployRemoteSitePhysicalPath="" msdeployAllowUntrustedCertificate="False" msdeploySkipExtraFilesOnServer="True" msdeployMarkAsApp="False" profileName="Release" publishMethod="FileSystem" replaceMatchingFiles="True" userName="" savePWD="False" userPWD="" SelectedForPublish="True">
    <file relUrl="Views/Shared/CallNavigationButtons.ascx" publishTime="07/22/2011 07:26:03" />
    <file relUrl="Content/font/Cicle_Shadow-webfont.svg" publishTime="07/22/2011 07:25:59" />
    <file relUrl="Views/EmailsForCall/Edit.aspx" publishTime="07/22/2011 07:26:03" />
    <file relUrl="Content/Common/Icons/page_white_text.png" publishTime="07/22/2011 07:25:59" />
    <file relUrl="bin/NPOI.POIFS.xml" publishTime="07/22/2011 07:25:55" />
    <file relUrl="Scripts/tiny_mce/plugins/advlink/link.htm" publishTime="07/22/2011 07:26:00" />
    <file relUrl="Content/images/ui-bg_inset-hard_100_fcfdfd_1x100.png" publishTime="07/22/2011 07:25:59" />
    <file relUrl="Content/Common/Icons/Mvc/TabStrip.png" publishTime="07/22/2011 07:25:59" />
    <file relUrl="Scripts/jquery.jqEasyCharCounter.min.js" publishTime="07/22/2011 07:26:00" />
    <file relUrl="bin/NHibernate.Validator.dll" publishTime="07/22/2011 07:25:54" />
    <file relUrl="Scripts/tiny_mce/plugins/wordcount/editor_plugin.js" publishTime="07/22/2011 07:26:02" />
    <file relUrl="Scripts/tiny_mce/themes/advanced/editor_template.js" publishTime="07/22/2011 07:26:02" />
    <file relUrl="Content/Common/Icons/Suites_32/CMS.png" publishTime="07/22/2011 07:25:59" />
    <file relUrl="Scripts/tiny_mce/plugins/table/editor_plugin_src.js" publishTime="07/22/2011 07:26:02" />
    <file relUrl="AppReleaseSettings.config" publishTime="03/28/2011 14:38:23" />
    <file relUrl="Scripts/tiny_mce/plugins/advlink/langs/en_dlg.js" publishTime="07/22/2011 07:26:00" />
    <file relUrl="Scripts/tiny_mce/plugins/emotions/img/smiley-tongue-out.gif" publishTime="07/22/2011 07:26:00" />
    <file relUrl="Scripts/tiny_mce/plugins/xhtmlxtras/abbr.htm" publishTime="07/22/2011 07:26:02" />
    <file relUrl="Scripts/tiny_mce/plugins/safari/editor_plugin_src.js" publishTime="07/22/2011 07:26:02" />
    <file relUrl="Scripts/tiny_mce/themes/advanced/skins/o2k7/img/button_bg_black.png" publishTime="07/22/2011 07:26:02" />
    <file relUrl="Scripts/tiny_mce/plugins/nonbreaking/editor_plugin.js" publishTime="07/22/2011 07:26:02" />
    <file relUrl="Scripts/jquery.CaesMutioptionControl.js" publishTime="07/22/2011 07:26:00" />
    <file relUrl="Images/arrow_fat_up.gif" publishTime="07/22/2011 07:26:00" />
    <file relUrl="Scripts/tiny_mce/plugins/preview/jscripts/embed.js" publishTime="07/22/2011 07:26:02" />
    <file relUrl="Scripts/tiny_mce/plugins/autosave/editor_plugin.js" publishTime="07/22/2011 07:26:00" />
    <file relUrl="Scripts/tiny_mce/plugins/wordcount/editor_plugin_src.js" publishTime="07/22/2011 07:26:02" />
    <file relUrl="Scripts/tiny_mce/plugins/advhr/langs/en_dlg.js" publishTime="07/22/2011 07:26:00" />
    <file relUrl="Views/EmailQueue/Details.aspx" publishTime="07/22/2011 07:26:03" />
    <file relUrl="Views/Report/TemplateIndex.aspx" publishTime="07/22/2011 07:26:03" />
    <file relUrl="Scripts/tiny_mce/themes/advanced/js/source_editor.js" publishTime="07/22/2011 07:26:02" />
    <file relUrl="Scripts/tiny_mce/themes/advanced/img/colorpicker.jpg" publishTime="07/22/2011 07:26:02" />
    <file relUrl="Content/Common/Icons/folder.png" publishTime="07/22/2011 07:25:59" />
    <file relUrl="Scripts/tiny_mce/themes/advanced/color_picker.htm" publishTime="07/22/2011 07:26:02" />
    <file relUrl="Content/images/ui-bg_gloss-wave_55_5c9ccc_500x100.png" publishTime="07/22/2011 07:25:59" />
    <file relUrl="Content/font/Cicle_Semi_Italic-webfont.ttf" publishTime="07/22/2011 07:25:59" />
    <file relUrl="Scripts/tiny_mce/plugins/preview/editor_plugin.js" publishTime="07/22/2011 07:26:02" />
    <file relUrl="Scripts/tiny_mce/plugins/table/css/row.css" publishTime="07/22/2011 07:26:02" />
    <file relUrl="Content/Common/Icons/Mvc/Grid.png" publishTime="07/22/2011 07:25:59" />
    <file relUrl="Scripts/tiny_mce/langs/en.js" publishTime="07/22/2011 07:26:00" />
    <file relUrl="Scripts/tiny_mce/plugins/visualchars/editor_plugin.js" publishTime="07/22/2011 07:26:02" />
    <file relUrl="Scripts/tiny_mce/utils/mctabs.js" publishTime="07/22/2011 07:26:03" />
    <file relUrl="Views/Home/LoggedOut.aspx" publishTime="07/22/2011 07:26:03" />
    <file relUrl="Content/Common/Icons/Suites_32/WPF.png" publishTime="07/22/2011 07:25:59" />
    <file relUrl="Scripts/tiny_mce/plugins/xhtmlxtras/css/attributes.css" publishTime="07/22/2011 07:26:02" />
    <file relUrl="Robots.txt" publishTime="07/22/2011 07:26:00" />
    <file relUrl="Scripts/tiny_mce/plugins/inlinepopups/editor_plugin_src.js" publishTime="07/22/2011 07:26:01" />
    <file relUrl="Scripts/tiny_mce/plugins/emotions/img/smiley-sealed.gif" publishTime="07/22/2011 07:26:00" />
    <file relUrl="Scripts/tiny_mce/themes/simple/langs/en.js" publishTime="07/22/2011 07:26:02" />
    <file relUrl="Scripts/tiny_mce/plugins/xhtmlxtras/attributes.htm" publishTime="07/22/2011 07:26:02" />
    <file relUrl="Content/Common/orm-comparison.png" publishTime="07/22/2011 07:25:59" />
    <file relUrl="Content/font/Cicle_Semi-webfont.woff" publishTime="07/22/2011 07:25:59" />
    <file relUrl="Scripts/tiny_mce/plugins/pagebreak/editor_plugin_src.js" publishTime="07/22/2011 07:26:02" />
    <file relUrl="Scripts/tiny_mce/plugins/pagebreak/img/trans.gif" publishTime="07/22/2011 07:26:02" />
    <file relUrl="Scripts/tiny_mce/plugins/emotions/js/emotions.js" publishTime="07/22/2011 07:26:00" />
    <file relUrl="Scripts/tiny_mce/plugins/emotions/img/smiley-smile.gif" publishTime="07/22/2011 07:26:00" />
    <file relUrl="Views/Editor/CreateReviewer.aspx" publishTime="07/22/2011 07:26:03" />
    <file relUrl="Views/Home/Index.aspx" publishTime="07/22/2011 07:26:03" />
    <file relUrl="Views/Investigator/Edit.aspx" publishTime="07/22/2011 07:26:03" />
    <file relUrl="Scripts/tiny_mce/plugins/media/js/media.js" publishTime="07/22/2011 07:26:02" />
    <file relUrl="Scripts/tiny_mce/plugins/fullpage/editor_plugin_src.js" publishTime="07/22/2011 07:26:00" />
    <file relUrl="Scripts/tiny_mce/plugins/contextmenu/editor_plugin.js" publishTime="07/22/2011 07:26:00" />
    <file relUrl="Scripts/tiny_mce/plugins/nonbreaking/editor_plugin_src.js" publishTime="07/22/2011 07:26:02" />
    <file relUrl="bin/Rhino.Mocks.dll" publishTime="07/22/2011 07:25:55" />
    <file relUrl="Content/Common/Icons/Suites_32/PD.png" publishTime="07/22/2011 07:25:59" />
    <file relUrl="Content/images/ui-bg_glass_85_dfeffc_1x400.png" publishTime="07/22/2011 07:25:59" />
    <file relUrl="Scripts/tiny_mce/plugins/autosave/editor_plugin_src.js" publishTime="07/22/2011 07:26:00" />
    <file relUrl="Scripts/MicrosoftAjax.debug.js" publishTime="07/22/2011 07:26:00" />
    <file relUrl="Views/Home/About.aspx" publishTime="07/22/2011 07:26:03" />
    <file relUrl="Scripts/tiny_mce/plugins/fullscreen/editor_plugin.js" publishTime="07/22/2011 07:26:01" />
    <file relUrl="Images/CheckMark-1.png" publishTime="07/22/2011 07:26:00" />
    <file relUrl="Scripts/tiny_mce/plugins/fullpage/langs/en_dlg.js" publishTime="07/22/2011 07:26:01" />
    <file relUrl="Gramps.Publish.xml" publishTime="08/10/2011 08:34:20" />
    <file relUrl="Scripts/tiny_mce/plugins/table/row.htm" publishTime="07/22/2011 07:26:02" />
    <file relUrl="Scripts/xVal.jquery.validate.js" publishTime="07/22/2011 07:26:03" />
    <file relUrl="Scripts/tiny_mce/plugins/tabfocus/editor_plugin.js" publishTime="07/22/2011 07:26:02" />
    <file relUrl="Scripts/tiny_mce/plugins/safari/editor_plugin.js" publishTime="07/22/2011 07:26:02" />
    <file relUrl="Scripts/tiny_mce/plugins/example/dialog.htm" publishTime="07/22/2011 07:26:00" />
    <file relUrl="Scripts/tiny_mce/plugins/xhtmlxtras/js/ins.js" publishTime="07/22/2011 07:26:02" />
    <file relUrl="Scripts/jquery-1.4.1.min.js" publishTime="07/22/2011 07:26:00" />
    <file relUrl="Content/font/Cicle_Semi_Italic-webfont.woff" publishTime="07/22/2011 07:25:59" />
    <file relUrl="Content/images/ui-bg_glass_75_d0e5f5_1x400.png" publishTime="07/22/2011 07:25:59" />
    <file relUrl="Scripts/tiny_mce/plugins/example/editor_plugin_src.js" publishTime="07/22/2011 07:26:00" />
    <file relUrl="Scripts/tiny_mce/plugins/table/js/row.js" publishTime="07/22/2011 07:26:02" />
    <file relUrl="bin/FluentNHibernate.dll" publishTime="07/22/2011 07:25:54" />
    <file relUrl="Images/big_print.png" publishTime="07/22/2011 07:26:00" />
    <file relUrl="bin/NPOI.Util.dll" publishTime="07/22/2011 07:25:55" />
    <file relUrl="Scripts/MicrosoftMvcAjax.js" publishTime="07/22/2011 07:26:00" />
    <file relUrl="Content/Common/Icons/Suites/mvc.png" publishTime="07/22/2011 07:25:59" />
    <file relUrl="Scripts/tiny_mce/plugins/fullpage/css/fullpage.css" publishTime="07/22/2011 07:26:00" />
    <file relUrl="Scripts/tiny_mce/plugins/table/js/cell.js" publishTime="07/22/2011 07:26:02" />
    <file relUrl="Scripts/tiny_mce/plugins/style/editor_plugin_src.js" publishTime="07/22/2011 07:26:02" />
    <file relUrl="Scripts/tiny_mce/themes/advanced/skins/default/content.css" publishTime="07/22/2011 07:26:02" />
    <file relUrl="bin/Gramps.pdb" publishTime="08/10/2011 08:42:10" />
    <file relUrl="Views/Shared/SystemMessage.ascx" publishTime="07/22/2011 07:26:03" />
    <file relUrl="Scripts/tiny_mce/themes/advanced/image.htm" publishTime="07/22/2011 07:26:02" />
    <file relUrl="Content/font/Cicle_Shadow-webfont.eot" publishTime="07/22/2011 07:25:59" />
    <file relUrl="Images/Rocket_launch.png" publishTime="07/22/2011 07:26:00" />
    <file relUrl="Content/font/Cicle_Fina-webfont.woff" publishTime="07/22/2011 07:25:59" />
    <file relUrl="Content/Common/Icons/Suites_32/JustCode.png" publishTime="07/22/2011 07:25:59" />
    <file relUrl="Scripts/tiny_mce/plugins/media/img/shockwave.gif" publishTime="07/22/2011 07:26:02" />
    <file relUrl="Content/Common/Icons/Suites_32/TFS.png" publishTime="07/22/2011 07:25:59" />
    <file relUrl="bin/NPOI.HSSF.dll" publishTime="07/22/2011 07:25:55" />
    <file relUrl="Scripts/tiny_mce/plugins/xhtmlxtras/js/del.js" publishTime="07/22/2011 07:26:02" />
    <file relUrl="Content/telerik.windows7.css" publishTime="07/22/2011 07:25:59" />
    <file relUrl="Scripts/tiny_mce/plugins/style/props.htm" publishTime="07/22/2011 07:26:02" />
    <file relUrl="Scripts/tiny_mce/plugins/media/img/windowsmedia.gif" publishTime="07/22/2011 07:26:02" />
    <file relUrl="Scripts/tiny_mce/plugins/layer/editor_plugin.js" publishTime="07/22/2011 07:26:01" />
    <file relUrl="Scripts/jquery.bt.min.js" publishTime="07/22/2011 07:26:00" />
    <file relUrl="Views/EmailQueue/Edit.aspx" publishTime="07/22/2011 07:26:03" />
    <file relUrl="Scripts/jquery.validate-vsdoc.js" publishTime="07/22/2011 07:26:00" />
    <file relUrl="Views/Template/Edit.aspx" publishTime="07/22/2011 07:26:03" />
    <file relUrl="Views/Report/ReportPropertyColumns.ascx" publishTime="07/22/2011 07:26:03" />
    <file relUrl="Content/jquery-ui-1.8.4.custom.css" publishTime="07/22/2011 07:25:59" />
    <file relUrl="bin/Castle.Core.dll" publishTime="07/22/2011 07:25:53" />
    <file relUrl="Views/Proposal/ProposalAnswerDetails.ascx" publishTime="07/22/2011 07:26:03" />
    <file relUrl="Views/Editor/EditReviewer.aspx" publishTime="07/22/2011 07:26:03" />
    <file relUrl="Content/images/ui-bg_glass_75.png" publishTime="07/22/2011 07:25:59" />
    <file relUrl="Content/Windows7/loading.gif" publishTime="07/22/2011 07:25:59" />
    <file relUrl="bin/MvcContrib.dll" publishTime="07/22/2011 07:25:54" />
    <file relUrl="Scripts/tiny_mce/plugins/advhr/rule.htm" publishTime="07/22/2011 07:26:00" />
    <file relUrl="Scripts/tiny_mce/plugins/fullpage/js/fullpage.js" publishTime="07/22/2011 07:26:01" />
    <file relUrl="Scripts/tiny_mce/plugins/pagebreak/img/pagebreak.gif" publishTime="07/22/2011 07:26:02" />
    <file relUrl="Scripts/tiny_mce/plugins/iespell/editor_plugin_src.js" publishTime="07/22/2011 07:26:01" />
    <file relUrl="Scripts/tiny_mce/plugins/searchreplace/searchreplace.htm" publishTime="07/22/2011 07:26:02" />
    <file relUrl="Content/font/Cicle_Shadow-webfont.woff" publishTime="07/22/2011 07:25:59" />
    <file relUrl="Scripts/tiny_mce/plugins/spellchecker/editor_plugin.js" publishTime="07/22/2011 07:26:02" />
    <file relUrl="bin/Elmah.dll" publishTime="07/22/2011 07:25:53" />
    <file relUrl="Scripts/tiny_mce/plugins/example/js/dialog.js" publishTime="07/22/2011 07:26:00" />
    <file relUrl="Content/Common/Icons/Mvc/PanelBar.png" publishTime="07/22/2011 07:25:59" />
    <file relUrl="Content/Common/Icons/Suites/win.png" publishTime="07/22/2011 07:25:59" />
    <file relUrl="Views/Question/SharedQuestionSetup.ascx" publishTime="07/22/2011 07:26:03" />
    <file relUrl="bin/Gramps.dll" publishTime="08/10/2011 08:42:10" />
    <file relUrl="Scripts/tiny_mce/plugins/save/editor_plugin.js" publishTime="07/22/2011 07:26:02" />
    <file relUrl="bin/NPOI.HPSF.dll" publishTime="07/22/2011 07:25:55" />
    <file relUrl="Content/font/Cicle_Semi-webfont.svg" publishTime="07/22/2011 07:25:59" />
    <file relUrl="Scripts/tiny_mce/plugins/inlinepopups/skins/clearlooks2/img/vertical.gif" publishTime="07/22/2011 07:26:01" />
    <file relUrl="Scripts/tiny_mce/plugins/style/css/props.css" publishTime="07/22/2011 07:26:02" />
    <file relUrl="Scripts/tiny_mce/plugins/xhtmlxtras/editor_plugin.js" publishTime="07/22/2011 07:26:02" />
    <file relUrl="Content/telerik.vista.css" publishTime="07/22/2011 07:25:59" />
    <file relUrl="Scripts/tiny_mce/plugins/template/langs/en_dlg.js" publishTime="07/22/2011 07:26:02" />
    <file relUrl="Views/Report/EditForCall.aspx" publishTime="07/22/2011 07:26:03" />
    <file relUrl="Scripts/tiny_mce/themes/advanced/skins/default/img/buttons.png" publishTime="07/22/2011 07:26:02" />
    <file relUrl="Content/Common/Icons/Ajax/Scheduler.png" publishTime="07/22/2011 07:25:59" />
    <file relUrl="Content/images/ui-bg_flat_55_fbec88_40x100.png" publishTime="07/22/2011 07:25:59" />
    <file relUrl="Scripts/tiny_mce/plugins/xhtmlxtras/ins.htm" publishTime="07/22/2011 07:26:02" />
    <file relUrl="Scripts/tiny_mce/themes/advanced/skins/o2k7/content.css" publishTime="07/22/2011 07:26:02" />
    <file relUrl="Scripts/tiny_mce/plugins/example/langs/en_dlg.js" publishTime="07/22/2011 07:26:00" />
    <file relUrl="Views/Public/ForgotPassword.aspx" publishTime="07/22/2011 07:26:03" />
    <file relUrl="Scripts/tiny_mce/plugins/xhtmlxtras/js/element_common.js" publishTime="07/22/2011 07:26:02" />
    <file relUrl="Views/EmailQueue/Index.aspx" publishTime="07/22/2011 07:26:03" />
    <file relUrl="Scripts/tiny_mce/plugins/xhtmlxtras/del.htm" publishTime="07/22/2011 07:26:02" />
    <file relUrl="Images/arrow_fat_down.gif" publishTime="07/22/2011 07:26:00" />
    <file relUrl="Scripts/RenameForArray.js" publishTime="07/22/2011 07:26:00" />
    <file relUrl="bin/NPOI.HPSF.xml" publishTime="07/22/2011 07:25:55" />
    <file relUrl="Scripts/tiny_mce/plugins/emotions/langs/en_dlg.js" publishTime="07/22/2011 07:26:00" />
    <file relUrl="favicon.ico" publishTime="07/22/2011 07:26:03" />
    <file relUrl="Content/Common/Icons/Mvc/Menu.png" publishTime="07/22/2011 07:25:59" />
    <file relUrl="Scripts/tiny_mce/plugins/example/editor_plugin.js" publishTime="07/22/2011 07:26:00" />
    <file relUrl="Scripts/tiny_mce/plugins/media/img/trans.gif" publishTime="07/22/2011 07:26:02" />
    <file relUrl="bin/NHibernate.dll" publishTime="07/22/2011 07:25:54" />
    <file relUrl="Scripts/tiny_mce/plugins/advhr/editor_plugin.js" publishTime="07/22/2011 07:26:00" />
    <file relUrl="Scripts/tiny_mce/themes/advanced/skins/default/img/tabs.gif" publishTime="07/22/2011 07:26:02" />
    <file relUrl="Scripts/tiny_mce/plugins/fullpage/fullpage.htm" publishTime="07/22/2011 07:26:00" />
    <file relUrl="Scripts/tiny_mce/plugins/emotions/img/smiley-wink.gif" publishTime="07/22/2011 07:26:00" />
    <file relUrl="Scripts/tiny_mce/plugins/searchreplace/css/searchreplace.css" publishTime="07/22/2011 07:26:02" />
    <file relUrl="Scripts/tiny_mce/plugins/paste/editor_plugin.js" publishTime="07/22/2011 07:26:02" />
    <file relUrl="bin/Spring.Core.dll" publishTime="07/22/2011 07:25:55" />
    <file relUrl="Scripts/tiny_mce/plugins/iespell/editor_plugin.js" publishTime="07/22/2011 07:26:01" />
    <file relUrl="bin/Iesi.Collections.dll" publishTime="07/22/2011 07:25:54" />
    <file relUrl="bin/Castle.Windsor.dll" publishTime="07/22/2011 07:25:53" />
    <file relUrl="Scripts/tiny_mce/plugins/searchreplace/editor_plugin_src.js" publishTime="07/22/2011 07:26:02" />
    <file relUrl="bin/Castle.DynamicProxy2.dll" publishTime="07/22/2011 07:25:53" />
    <file relUrl="Scripts/tiny_mce/plugins/table/css/table.css" publishTime="07/22/2011 07:26:02" />
    <file relUrl="Images/Page_excel.png" publishTime="07/22/2011 07:26:00" />
    <file relUrl="Scripts/tiny_mce/plugins/inlinepopups/skins/clearlooks2/window.css" publishTime="07/22/2011 07:26:01" />
    <file relUrl="Scripts/tiny_mce/plugins/advlink/editor_plugin.js" publishTime="07/22/2011 07:26:00" />
    <file relUrl="Scripts/tiny_mce/plugins/bbcode/editor_plugin.js" publishTime="07/22/2011 07:26:00" />
    <file relUrl="Scripts/tiny_mce/plugins/paste/pasteword.htm" publishTime="07/22/2011 07:26:02" />
    <file relUrl="bin/MvcContrib.Castle.dll" publishTime="07/22/2011 07:25:54" />
    <file relUrl="Content/font/Cicle_Semi-webfont.eot" publishTime="07/22/2011 07:25:59" />
    <file relUrl="Scripts/tiny_mce/plugins/media/img/realmedia.gif" publishTime="07/22/2011 07:26:02" />
    <file relUrl="Scripts/tiny_mce/license.txt" publishTime="07/22/2011 07:26:00" />
    <file relUrl="Scripts/tiny_mce/themes/advanced/skins/default/img/progress.gif" publishTime="07/22/2011 07:26:02" />
    <file relUrl="Content/Common/Icons/Suites_32/WinForms.png" publishTime="07/22/2011 07:25:59" />
    <file relUrl="Scripts/tiny_mce/plugins/advimage/css/advimage.css" publishTime="07/22/2011 07:26:00" />
    <file relUrl="Scripts/jquery.enableTinyMce.js" publishTime="07/22/2011 07:26:00" />
    <file relUrl="Views/Proposal/AdminEdit.aspx" publishTime="08/05/2011 07:35:12" />
    <file relUrl="Content/Common/Icons/Sl/Chart.gif" publishTime="07/22/2011 07:25:59" />
    <file relUrl="Global.asax" publishTime="07/22/2011 07:26:00" />
    <file relUrl="Scripts/tiny_mce/themes/advanced/charmap.htm" publishTime="07/22/2011 07:26:02" />
    <file relUrl="Scripts/tiny_mce/plugins/print/editor_plugin_src.js" publishTime="07/22/2011 07:26:02" />
    <file relUrl="Scripts/tiny_mce/plugins/insertdatetime/editor_plugin_src.js" publishTime="07/22/2011 07:26:01" />
    <file relUrl="Scripts/tiny_mce/themes/advanced/skins/o2k7/ui_black.css" publishTime="07/22/2011 07:26:02" />
    <file relUrl="Scripts/tiny_mce/themes/simple/editor_template_src.js" publishTime="07/22/2011 07:26:02" />
    <file relUrl="Scripts/tiny_mce/themes/advanced/about.htm" publishTime="07/22/2011 07:26:02" />
    <file relUrl="bin/NPOI.Util.xml" publishTime="07/22/2011 07:25:55" />
    <file relUrl="Scripts/tiny_mce/plugins/advimage/langs/en_dlg.js" publishTime="07/22/2011 07:26:00" />
    <file relUrl="Views/Web.config" publishTime="07/22/2011 07:26:03" />
    <file relUrl="bin/Recaptcha.pdb" publishTime="07/22/2011 07:25:55" />
    <file relUrl="Images/CheckMark.png" publishTime="07/22/2011 07:26:00" />
    <file relUrl="Views/CallForProposal/Create.aspx" publishTime="07/22/2011 07:26:03" />
    <file relUrl="Scripts/tiny_mce/plugins/emotions/img/smiley-surprised.gif" publishTime="07/22/2011 07:26:00" />
    <file relUrl="Content/images/ui-icons_217bc0_256x240.png" publishTime="07/22/2011 07:25:59" />
    <file relUrl="Views/Shared/PublicLogOnUserControl.ascx" publishTime="07/22/2011 07:26:03" />
    <file relUrl="Content/font/Cicle_Gordita_Italic-webfont.ttf" publishTime="07/22/2011 07:25:59" />
    <file relUrl="Scripts/tiny_mce/plugins/example/img/example.gif" publishTime="07/22/2011 07:26:00" />
    <file relUrl="Scripts/tiny_mce/plugins/xhtmlxtras/js/acronym.js" publishTime="07/22/2011 07:26:02" />
    <file relUrl="Scripts/tiny_mce/themes/advanced/skins/o2k7/img/button_bg_silver.png" publishTime="07/22/2011 07:26:02" />
    <file relUrl="Views/Question/Create.aspx" publishTime="07/22/2011 07:26:03" />
    <file relUrl="Scripts/tiny_mce/plugins/directionality/editor_plugin.js" publishTime="07/22/2011 07:26:00" />
    <file relUrl="Content/Common/Icons/edit.png" publishTime="07/22/2011 07:25:59" />
    <file relUrl="Images/cancled_transparent.png" publishTime="07/22/2011 07:26:00" />
    <file relUrl="Scripts/tiny_mce/plugins/emotions/img/smiley-innocent.gif" publishTime="07/22/2011 07:26:00" />
    <file relUrl="Scripts/tiny_mce/plugins/advlink/css/advlink.css" publishTime="07/22/2011 07:26:00" />
    <file relUrl="bin/HibernatingRhinos.Profiler.Appender.dll" publishTime="07/22/2011 07:25:54" />
    <file relUrl="Content/Common/Icons/Suites/orm.png" publishTime="07/22/2011 07:25:59" />
    <file relUrl="Content/Common/Icons/Ajax/Grid.png" publishTime="07/22/2011 07:25:59" />
    <file relUrl="Content/font/Cicle_Gordita_Italic-webfont.svg" publishTime="07/22/2011 07:25:59" />
    <file relUrl="Scripts/tiny_mce/plugins/media/img/flv_player.swf" publishTime="07/22/2011 07:26:02" />
    <file relUrl="Content/font/Cicle_Gordita-webfont.woff" publishTime="07/22/2011 07:25:59" />
    <file relUrl="AppDebugSettings.config" publishTime="03/28/2011 14:38:23" />
    <file relUrl="Images/loading.gif" publishTime="07/22/2011 07:26:00" />
    <file relUrl="Scripts/tiny_mce/plugins/pagebreak/css/content.css" publishTime="07/22/2011 07:26:02" />
    <file relUrl="bin/NPOI.HSSF.xml" publishTime="07/22/2011 07:25:55" />
    <file relUrl="Scripts/tiny_mce/plugins/emotions/img/smiley-undecided.gif" publishTime="07/22/2011 07:26:00" />
    <file relUrl="Scripts/tiny_mce/plugins/template/editor_plugin.js" publishTime="07/22/2011 07:26:02" />
    <file relUrl="Content/font/Cicle_Gordita_Italic-webfont.eot" publishTime="07/22/2011 07:25:59" />
    <file relUrl="Views/CallForProposal/Launch.aspx" publishTime="07/22/2011 07:26:03" />
    <file relUrl="Scripts/tiny_mce/themes/advanced/link.htm" publishTime="07/22/2011 07:26:02" />
    <file relUrl="Content/font/Cicle_Gordita-webfont.svg" publishTime="07/22/2011 07:25:59" />
    <file relUrl="Scripts/tiny_mce/plugins/xhtmlxtras/js/attributes.js" publishTime="07/22/2011 07:26:02" />
    <file relUrl="bin/Microsoft.ReportViewer.WebForms.xml" publishTime="07/22/2011 07:25:54" />
    <file relUrl="Scripts/tiny_mce/plugins/spellchecker/editor_plugin_src.js" publishTime="07/22/2011 07:26:02" />
    <file relUrl="Content/Common/Icons/Suites/rep.png" publishTime="07/22/2011 07:25:59" />
    <file relUrl="Scripts/tiny_mce/themes/advanced/js/about.js" publishTime="07/22/2011 07:26:02" />
    <file relUrl="Scripts/tiny_mce/plugins/style/js/props.js" publishTime="07/22/2011 07:26:02" />
    <file relUrl="Scripts/tiny_mce/plugins/emotions/img/smiley-yell.gif" publishTime="07/22/2011 07:26:00" />
    <file relUrl="Scripts/tiny_mce/plugins/template/editor_plugin_src.js" publishTime="07/22/2011 07:26:02" />
    <file relUrl="Views/Account/LogOn.aspx" publishTime="07/22/2011 07:26:03" />
    <file relUrl="bin/Microsoft.ReportViewer.Common.dll" publishTime="07/22/2011 07:25:54" />
    <file relUrl="bin/Newtonsoft.Json.dll" publishTime="07/22/2011 07:25:55" />
    <file relUrl="Scripts/tiny_mce/plugins/emotions/editor_plugin.js" publishTime="07/22/2011 07:26:00" />
    <file relUrl="bin/Telerik.Web.Mvc.dll" publishTime="07/22/2011 07:25:56" />
    <file relUrl="Scripts/tiny_mce/plugins/tabfocus/editor_plugin_src.js" publishTime="07/22/2011 07:26:02" />
    <file relUrl="Content/font/Cicle_Gordita-webfont.ttf" publishTime="07/22/2011 07:25:59" />
    <file relUrl="bin/Common.Logging.dll" publishTime="07/22/2011 07:25:53" />
    <file relUrl="Scripts/tiny_mce/plugins/bbcode/editor_plugin_src.js" publishTime="07/22/2011 07:26:00" />
    <file relUrl="Views/EmailTemplate/Index.aspx" publishTime="07/22/2011 07:26:03" />
    <file relUrl="Scripts/tiny_mce/plugins/table/langs/en_dlg.js" publishTime="07/22/2011 07:26:02" />
    <file relUrl="Content/font/Cicle_Gordita_Italic-webfont.woff" publishTime="07/22/2011 07:25:59" />
    <file relUrl="Views/Report/CreateForTemplate.aspx" publishTime="07/22/2011 07:26:03" />
    <file relUrl="Images/logo-caes.png" publishTime="07/22/2011 07:26:00" />
    <file relUrl="Scripts/tiny_mce/plugins/advhr/js/rule.js" publishTime="07/22/2011 07:26:00" />
    <file relUrl="Views/EmailsForCall/Create.aspx" publishTime="07/22/2011 07:26:03" />
    <file relUrl="Views/Editor/Index.aspx" publishTime="07/22/2011 07:26:03" />
    <file relUrl="Images/small_print.png" publishTime="07/22/2011 07:26:00" />
    <file relUrl="Scripts/tiny_mce/themes/advanced/langs/en.js" publishTime="07/22/2011 07:26:02" />
    <file relUrl="bin/Gramps.Core.dll" publishTime="08/10/2011 08:42:07" />
    <file relUrl="Scripts/tiny_mce/plugins/xhtmlxtras/editor_plugin_src.js" publishTime="07/22/2011 07:26:02" />
    <file relUrl="Views/Proposal/Create.aspx" publishTime="07/22/2011 10:19:13" />
    <file relUrl="Views/Error/Index.aspx" publishTime="07/22/2011 07:26:03" />
    <file relUrl="Scripts/tiny_mce/plugins/inlinepopups/skins/clearlooks2/img/horizontal.gif" publishTime="07/22/2011 07:26:01" />
    <file relUrl="Scripts/tiny_mce/plugins/table/js/merge_cells.js" publishTime="07/22/2011 07:26:02" />
    <file relUrl="Content/Common/Icons/Suites_32/AJAX.png" publishTime="07/22/2011 07:25:59" />
    <file relUrl="Scripts/tiny_mce/themes/advanced/anchor.htm" publishTime="07/22/2011 07:26:02" />
    <file relUrl="Scripts/tiny_mce/plugins/fullscreen/fullscreen.htm" publishTime="07/22/2011 07:26:01" />
    <file relUrl="Views/Shared/NavigationButtons.ascx" publishTime="07/22/2011 07:26:03" />
    <file relUrl="Scripts/tiny_mce/plugins/style/editor_plugin.js" publishTime="07/22/2011 07:26:02" />
    <file relUrl="bin/UCDArch.dll" publishTime="07/22/2011 07:25:56" />
    <file relUrl="bin/Microsoft.Web.Mvc.dll" publishTime="07/22/2011 07:25:54" />
    <file relUrl="Scripts/tiny_mce/plugins/table/table.htm" publishTime="07/22/2011 07:26:02" />
    <file relUrl="Scripts/tiny_mce/plugins/autoresize/editor_plugin.js" publishTime="07/22/2011 07:26:00" />
    <file relUrl="Views/Question/Edit.aspx" publishTime="07/22/2011 07:26:03" />
    <file relUrl="Scripts/tiny_mce/themes/advanced/skins/o2k7/ui.css" publishTime="07/22/2011 07:26:02" />
    <file relUrl="Scripts/tiny_mce/plugins/searchreplace/langs/en_dlg.js" publishTime="07/22/2011 07:26:02" />
    <file relUrl="Scripts/tiny_mce/themes/simple/img/icons.gif" publishTime="07/22/2011 07:26:02" />
    <file relUrl="Content/jquery.bt.css" publishTime="07/22/2011 07:25:59" />
    <file relUrl="Scripts/tiny_mce/themes/advanced/editor_template_src.js" publishTime="07/22/2011 07:26:02" />
    <file relUrl="Images/logo-ucdavis.png" publishTime="07/22/2011 07:26:00" />
    <file relUrl="Views/EmailTemplate/Edit.aspx" publishTime="07/22/2011 07:26:03" />
    <file relUrl="Scripts/tiny_mce/themes/simple/skins/o2k7/ui.css" publishTime="07/22/2011 07:26:02" />
    <file relUrl="Scripts/jquery.jqEasyCharCounter.js" publishTime="07/22/2011 07:26:00" />
    <file relUrl="Content/images/ui-bg_inset-hard_100_f5f8f9_1x100.png" publishTime="07/22/2011 07:25:59" />
    <file relUrl="Scripts/tiny_mce/plugins/template/css/template.css" publishTime="07/22/2011 07:26:02" />
    <file relUrl="Scripts/tiny_mce/plugins/inlinepopups/skins/clearlooks2/img/alert.gif" publishTime="07/22/2011 07:26:01" />
    <file relUrl="Scripts/tiny_mce/plugins/print/editor_plugin.js" publishTime="07/22/2011 07:26:02" />
    <file relUrl="Scripts/tiny_mce/themes/advanced/js/charmap.js" publishTime="07/22/2011 07:26:02" />
    <file relUrl="Views/Question/SharedQuestionFields.ascx" publishTime="07/22/2011 07:26:03" />
    <file relUrl="Scripts/tiny_mce/plugins/noneditable/editor_plugin.js" publishTime="07/22/2011 07:26:02" />
    <file relUrl="Content/Common/Icons/Suites_32/MVC.png" publishTime="07/22/2011 07:25:59" />
    <file relUrl="Scripts/tiny_mce/plugins/advimage/editor_plugin_src.js" publishTime="07/22/2011 07:26:00" />
    <file relUrl="Scripts/tiny_mce/plugins/media/editor_plugin_src.js" publishTime="07/22/2011 07:26:01" />
    <file relUrl="Views/EmailsForCall/Index.aspx" publishTime="07/22/2011 07:26:03" />
    <file relUrl="Content/font/Cicle_Fina_Italic-webfont.svg" publishTime="07/22/2011 07:25:59" />
    <file relUrl="Views/CallForProposal/Edit.aspx" publishTime="07/22/2011 07:26:03" />
    <file relUrl="Scripts/tiny_mce/tiny_mce.js" publishTime="07/22/2011 07:26:03" />
    <file relUrl="Content/font/Cicle_Fina-webfont.svg" publishTime="07/22/2011 07:25:59" />
    <file relUrl="Views/Report/ReportFormForTemplate.ascx" publishTime="08/05/2011 07:35:13" />
    <file relUrl="Scripts/tiny_mce/tiny_mce_popup.js" publishTime="07/22/2011 07:26:03" />
    <file relUrl="Scripts/tiny_mce/themes/advanced/skins/default/dialog.css" publishTime="07/22/2011 07:26:02" />
    <file relUrl="bin/NPOI.dll" publishTime="07/22/2011 07:25:55" />
    <file relUrl="Scripts/tiny_mce/tiny_mce_src.js" publishTime="07/22/2011 07:26:03" />
    <file relUrl="Content/Common/Icons/Sl/Scheduler.gif" publishTime="07/22/2011 07:25:59" />
    <file relUrl="Content/font/Cicle_Semi_Italic-webfont.eot" publishTime="07/22/2011 07:25:59" />
    <file relUrl="bin/NPOI.DDF.dll" publishTime="07/22/2011 07:25:54" />
    <file relUrl="Content/Common/Icons/Sl/GridView.gif" publishTime="07/22/2011 07:25:59" />
    <file relUrl="Scripts/jquery.validate.js" publishTime="07/22/2011 07:26:00" />
    <file relUrl="Scripts/tiny_mce/themes/advanced/js/image.js" publishTime="07/22/2011 07:26:02" />
    <file relUrl="Scripts/tiny_mce/plugins/media/css/content.css" publishTime="07/22/2011 07:26:01" />
    <file relUrl="Scripts/tiny_mce/plugins/emotions/img/smiley-kiss.gif" publishTime="07/22/2011 07:26:00" />
    <file relUrl="Scripts/tiny_mce/plugins/inlinepopups/skins/clearlooks2/img/confirm.gif" publishTime="07/22/2011 07:26:01" />
    <file relUrl="Scripts/tiny_mce/plugins/contextmenu/editor_plugin_src.js" publishTime="07/22/2011 07:26:00" />
    <file relUrl="bin/NPOI.POIFS.dll" publishTime="07/22/2011 07:25:55" />
    <file relUrl="Images/Details.png" publishTime="07/22/2011 07:26:00" />
    <file relUrl="Scripts/jquery-1.4.1-vsdoc.js" publishTime="07/22/2011 07:26:00" />
    <file relUrl="Scripts/tiny_mce/plugins/advhr/css/advhr.css" publishTime="07/22/2011 07:26:00" />
    <file relUrl="Scripts/tiny_mce/plugins/paste/langs/en_dlg.js" publishTime="07/22/2011 07:26:02" />
    <file relUrl="Scripts/tiny_mce/plugins/fullpage/editor_plugin.js" publishTime="07/22/2011 07:26:00" />
    <file relUrl="Scripts/tiny_mce/plugins/example/langs/en.js" publishTime="07/22/2011 07:26:00" />
    <file relUrl="Scripts/tiny_mce/plugins/table/merge_cells.htm" publishTime="07/22/2011 07:26:02" />
    <file relUrl="Scripts/tiny_mce/plugins/table/js/table.js" publishTime="07/22/2011 07:26:02" />
    <file relUrl="Scripts/tiny_mce/themes/simple/skins/o2k7/img/button_bg.png" publishTime="07/22/2011 07:26:02" />
    <file relUrl="Content/images/ui-icons_d8e7f3_256x240.png" publishTime="07/22/2011 07:25:59" />
    <file relUrl="bin/log4net.dll" publishTime="07/22/2011 07:25:56" />
    <file relUrl="Views/Report/EditForTemplate.aspx" publishTime="07/22/2011 07:26:03" />
    <file relUrl="Views/Shared/LogOnUserControl.ascx" publishTime="07/22/2011 07:26:03" />
    <file relUrl="Content/font/Cicle_Fina_Italic-webfont.woff" publishTime="07/22/2011 07:25:59" />
    <file relUrl="Scripts/tiny_mce/themes/advanced/skins/default/ui.css" publishTime="07/22/2011 07:26:02" />
    <file relUrl="Views/Proposal/Details.aspx" publishTime="08/02/2011 11:30:13" />
    <file relUrl="Views/Public/ChangePasswordSuccess.aspx" publishTime="07/22/2011 07:26:03" />
    <file relUrl="Scripts/tiny_mce/plugins/xhtmlxtras/js/cite.js" publishTime="07/22/2011 07:26:02" />
    <file relUrl="Scripts/tiny_mce/plugins/table/css/cell.css" publishTime="07/22/2011 07:26:02" />
    <file relUrl="Scripts/tiny_mce/plugins/xhtmlxtras/css/popup.css" publishTime="07/22/2011 07:26:02" />
    <file relUrl="Views/Shared/Site.Master" publishTime="07/22/2011 07:26:03" />
    <file relUrl="Scripts/MicrosoftMvcAjax.debug.js" publishTime="07/22/2011 07:26:00" />
    <file relUrl="Scripts/tiny_mce/themes/simple/skins/default/ui.css" publishTime="07/22/2011 07:26:02" />
    <file relUrl="packages.config" publishTime="07/22/2011 07:26:03" />
    <file relUrl="Views/Report/CreateForCall.aspx" publishTime="07/22/2011 07:26:03" />
    <file relUrl="Scripts/tiny_mce/themes/advanced/skins/default/img/items.gif" publishTime="07/22/2011 07:26:02" />
    <file relUrl="Scripts/tiny_mce/plugins/table/cell.htm" publishTime="07/22/2011 07:26:02" />
    <file relUrl="bin/Microsoft.Practices.ServiceLocation.dll" publishTime="07/22/2011 07:25:54" />
    <file relUrl="Images/plus.png" publishTime="07/22/2011 07:26:00" />
    <file relUrl="Content/font.css" publishTime="07/22/2011 07:25:59" />
    <file relUrl="Views/EmailsForCall/BulkCreate.aspx" publishTime="07/22/2011 07:26:03" />
    <file relUrl="Views/Report/CallIndex.aspx" publishTime="07/22/2011 07:26:03" />
    <file relUrl="Scripts/tiny_mce/themes/advanced/js/link.js" publishTime="07/22/2011 07:26:02" />
    <file relUrl="Views/Proposal/Home.aspx" publishTime="07/22/2011 07:26:03" />
    <file relUrl="Content/font/Cicle_Semi_Italic-webfont.svg" publishTime="07/22/2011 07:25:59" />
    <file relUrl="Content/font/Cicle_Semi-webfont.ttf" publishTime="07/22/2011 07:25:59" />
    <file relUrl="Content/Site.css" publishTime="07/22/2011 07:25:59" />
    <file relUrl="Content/font/Cicle_Fina-webfont.ttf" publishTime="07/22/2011 07:25:59" />
    <file relUrl="Content/Common/Icons/Suites/sl.png" publishTime="07/22/2011 07:25:59" />
    <file relUrl="Views/Editor/SendCall.aspx" publishTime="07/22/2011 07:26:03" />
    <file relUrl="Scripts/tiny_mce/themes/advanced/img/icons.gif" publishTime="07/22/2011 07:26:02" />
    <file relUrl="Scripts/tiny_mce/plugins/preview/preview.html" publishTime="07/22/2011 07:26:02" />
    <file relUrl="bin/MvcContrib.FluentHtml.dll" publishTime="07/22/2011 07:25:54" />
    <file relUrl="Images/logo.jpg" publishTime="07/22/2011 07:26:00" />
    <file relUrl="Scripts/tiny_mce/plugins/table/editor_plugin.js" publishTime="07/22/2011 07:26:02" />
    <file relUrl="Scripts/tiny_mce/plugins/save/editor_plugin_src.js" publishTime="07/22/2011 07:26:02" />
    <file relUrl="Content/images/ui-bg_glass_95_fef1ec_1x400.png" publishTime="07/22/2011 07:25:59" />
    <file relUrl="Scripts/tiny_mce/plugins/paste/js/pastetext.js" publishTime="07/22/2011 07:26:02" />
    <file relUrl="Scripts/tiny_mce/themes/simple/skins/default/content.css" publishTime="07/22/2011 07:26:02" />
    <file relUrl="AppTestSettings.config" publishTime="03/28/2011 14:38:23" />
    <file relUrl="Scripts/tiny_mce/plugins/media/langs/en_dlg.js" publishTime="07/22/2011 07:26:02" />
    <file relUrl="Images/Cancel-1.png" publishTime="07/22/2011 07:26:00" />
    <file relUrl="Scripts/tiny_mce/plugins/xhtmlxtras/acronym.htm" publishTime="07/22/2011 07:26:02" />
    <file relUrl="Scripts/tiny_mce/plugins/emotions/img/smiley-cool.gif" publishTime="07/22/2011 07:26:00" />
    <file relUrl="Views/Shared/Error.aspx" publishTime="07/22/2011 07:26:03" />
    <file relUrl="Scripts/tiny_mce/plugins/inlinepopups/skins/clearlooks2/img/corners.gif" publishTime="07/22/2011 07:26:01" />
    <file relUrl="Content/images/ui-icons_2e83ff_256x240.png" publishTime="07/22/2011 07:25:59" />
    <file relUrl="Scripts/tiny_mce/plugins/media/css/media.css" publishTime="07/22/2011 07:26:01" />
    <file relUrl="Content/Common/Icons/Ajax/Editor.png" publishTime="07/22/2011 07:25:59" />
    <file relUrl="bin/Spring.Aop.dll" publishTime="07/22/2011 07:25:55" />
    <file relUrl="Views/Proposal/AdminIndex.aspx" publishTime="08/05/2011 07:35:13" />
    <file relUrl="Views/Template/Index.aspx" publishTime="07/22/2011 07:26:03" />
    <file relUrl="Content/font/Cicle_Fina_Italic-webfont.ttf" publishTime="07/22/2011 07:25:59" />
    <file relUrl="Views/Report/ReportFormForCall.ascx" publishTime="08/05/2011 07:35:13" />
    <file relUrl="Scripts/tiny_mce/plugins/inlinepopups/skins/clearlooks2/img/button.gif" publishTime="07/22/2011 07:26:01" />
    <file relUrl="Scripts/tiny_mce/themes/advanced/skins/o2k7/ui_silver.css" publishTime="07/22/2011 07:26:02" />
    <file relUrl="Scripts/tiny_mce/plugins/preview/example.html" publishTime="07/22/2011 07:26:02" />
    <file relUrl="Content/Common/Icons/Suites/test.png" publishTime="07/22/2011 07:25:59" />
    <file relUrl="Content/font/Cicle_Shadow-webfont.ttf" publishTime="07/22/2011 07:25:59" />
    <file relUrl="Scripts/tiny_mce/plugins/emotions/img/smiley-frown.gif" publishTime="07/22/2011 07:26:00" />
    <file relUrl="Content/telerik.common.css" publishTime="07/22/2011 07:25:59" />
    <file relUrl="Content/Common/sprite.png" publishTime="07/22/2011 07:25:59" />
    <file relUrl="Scripts/tiny_mce/plugins/spellchecker/css/content.css" publishTime="07/22/2011 07:26:02" />
    <file relUrl="Scripts/tiny_mce/themes/advanced/langs/en_dlg.js" publishTime="07/22/2011 07:26:02" />
    <file relUrl="Scripts/tiny_mce/plugins/safari/blank.htm" publishTime="07/22/2011 07:26:02" />
    <file relUrl="Content/Common/Icons/Suites/wpf.png" publishTime="07/22/2011 07:25:59" />
    <file relUrl="Scripts/tiny_mce/plugins/media/js/embed.js" publishTime="07/22/2011 07:26:02" />
    <file relUrl="Views/Question/SharedQuestionSample.ascx" publishTime="07/22/2011 07:26:03" />
    <file relUrl="Content/Vista/sprite.png" publishTime="07/22/2011 07:25:59" />
    <file relUrl="Scripts/tiny_mce/plugins/inlinepopups/template.htm" publishTime="07/22/2011 07:26:01" />
    <file relUrl="Scripts/tiny_mce/themes/advanced/skins/default/img/menu_check.gif" publishTime="07/22/2011 07:26:02" />
    <file relUrl="Views/Proposal/Edit.aspx" publishTime="08/05/2011 07:35:13" />
    <file relUrl="Scripts/tiny_mce/plugins/directionality/editor_plugin_src.js" publishTime="07/22/2011 07:26:00" />
    <file relUrl="Scripts/tiny_mce/plugins/inlinepopups/editor_plugin.js" publishTime="07/22/2011 07:26:01" />
    <file relUrl="Scripts/tiny_mce/plugins/inlinepopups/skins/clearlooks2/img/buttons.gif" publishTime="07/22/2011 07:26:01" />
    <file relUrl="Scripts/tiny_mce/plugins/paste/pastetext.htm" publishTime="07/22/2011 07:26:02" />
    <file relUrl="Scripts/tiny_mce/plugins/style/langs/en_dlg.js" publishTime="07/22/2011 07:26:02" />
    <file relUrl="Content/Common/Icons/Suites_32/REP.png" publishTime="07/22/2011 07:25:59" />
    <file relUrl="Scripts/tiny_mce/utils/form_utils.js" publishTime="07/22/2011 07:26:03" />
    <file relUrl="bin/Castle.MicroKernel.dll" publishTime="07/22/2011 07:25:53" />
    <file relUrl="bin/Gramps.Core.pdb" publishTime="08/10/2011 08:42:06" />
    <file relUrl="Scripts/tiny_mce/plugins/searchreplace/js/searchreplace.js" publishTime="07/22/2011 07:26:02" />
    <file relUrl="Content/Vista/loading.gif" publishTime="07/22/2011 07:25:59" />
    <file relUrl="Scripts/tiny_mce/plugins/xhtmlxtras/cite.htm" publishTime="07/22/2011 07:26:02" />
    <file relUrl="bin/xVal.dll" publishTime="07/22/2011 07:25:56" />
    <file relUrl="Scripts/tiny_mce/plugins/advlink/editor_plugin_src.js" publishTime="07/22/2011 07:26:00" />
    <file relUrl="Content/font/Cicle_Fina-webfont.eot" publishTime="07/22/2011 07:25:59" />
    <file relUrl="Scripts/tiny_mce/plugins/searchreplace/editor_plugin.js" publishTime="07/22/2011 07:26:02" />
    <file relUrl="bin/NHibernate.Linq.dll" publishTime="07/22/2011 07:25:54" />
    <file relUrl="Views/Question/Index.aspx" publishTime="07/22/2011 07:26:03" />
    <file relUrl="Scripts/tiny_mce/jquery.tinymce.js" publishTime="07/22/2011 07:26:00" />
    <file relUrl="Views/CallForProposal/Index.aspx" publishTime="08/05/2011 07:35:12" />
    <file relUrl="Content/images/ui-icons_469bdd_256x240.png" publishTime="07/22/2011 07:25:59" />
    <file relUrl="Scripts/MicrosoftMvcValidation.js" publishTime="07/22/2011 07:26:00" />
    <file relUrl="Scripts/tiny_mce/plugins/emotions/img/smiley-money-mouth.gif" publishTime="07/22/2011 07:26:00" />
    <file relUrl="Scripts/tiny_mce/plugins/layer/editor_plugin_src.js" publishTime="07/22/2011 07:26:01" />
    <file relUrl="Scripts/tiny_mce/utils/editable_selects.js" publishTime="07/22/2011 07:26:03" />
    <file relUrl="Scripts/tiny_mce/themes/simple/editor_template.js" publishTime="07/22/2011 07:26:02" />
    <file relUrl="Scripts/tiny_mce/plugins/noneditable/editor_plugin_src.js" publishTime="07/22/2011 07:26:02" />
    <file relUrl="Scripts/tiny_mce/plugins/emotions/img/smiley-laughing.gif" publishTime="07/22/2011 07:26:00" />
    <file relUrl="Content/images/ui-bg_flat_0_aaaaaa_40x100.png" publishTime="07/22/2011 07:25:59" />
    <file relUrl="Scripts/tiny_mce/plugins/emotions/editor_plugin_src.js" publishTime="07/22/2011 07:26:00" />
    <file relUrl="Scripts/tiny_mce/themes/advanced/js/color_picker.js" publishTime="07/22/2011 07:26:02" />
    <file relUrl="bin/NHibernate.ByteCode.Spring.dll" publishTime="07/22/2011 07:25:54" />
    <file relUrl="Scripts/tiny_mce/plugins/advhr/editor_plugin_src.js" publishTime="07/22/2011 07:26:00" />
    <file relUrl="Views/Proposal/ReviewerIndex.aspx" publishTime="08/05/2011 07:35:13" />
    <file relUrl="Scripts/tiny_mce/plugins/emotions/emotions.htm" publishTime="07/22/2011 07:26:00" />
    <file relUrl="Views/Public/ChangePassword.aspx" publishTime="07/22/2011 07:26:03" />
    <file relUrl="Scripts/tiny_mce/plugins/template/template.htm" publishTime="07/22/2011 07:26:02" />
    <file relUrl="Scripts/tiny_mce/plugins/template/js/template.js" publishTime="07/22/2011 07:26:02" />
    <file relUrl="Content/images/ui-icons_6da8d5_256x240.png" publishTime="07/22/2011 07:25:59" />
    <file relUrl="Views/Investigator/InvestigatorForm.ascx" publishTime="07/22/2011 07:26:03" />
    <file relUrl="Scripts/jquery-1.4.1.js" publishTime="07/22/2011 07:26:00" />
    <file relUrl="Scripts/tiny_mce/plugins/media/media.htm" publishTime="07/22/2011 07:26:02" />
    <file relUrl="Views/Template/Create.aspx" publishTime="07/22/2011 07:26:03" />
    <file relUrl="Views/Editor/AddEditor.aspx" publishTime="07/22/2011 07:26:03" />
    <file relUrl="Scripts/tiny_mce/plugins/visualchars/editor_plugin_src.js" publishTime="07/22/2011 07:26:02" />
    <file relUrl="Content/Common/Icons/delete.png" publishTime="07/22/2011 07:25:59" />
    <file relUrl="Scripts/tiny_mce/plugins/advimage/image.htm" publishTime="07/22/2011 07:26:00" />
    <file relUrl="Scripts/tiny_mce/plugins/autoresize/editor_plugin_src.js" publishTime="07/22/2011 07:26:00" />
    <file relUrl="Scripts/tiny_mce/themes/advanced/skins/o2k7/img/button_bg.png" publishTime="07/22/2011 07:26:02" />
    <file relUrl="Scripts/tiny_mce/plugins/paste/editor_plugin_src.js" publishTime="07/22/2011 07:26:02" />
    <file relUrl="Scripts/tiny_mce/plugins/template/blank.htm" publishTime="07/22/2011 07:26:02" />
    <file relUrl="Scripts/jquery.validate.min.js" publishTime="07/22/2011 07:26:00" />
    <file relUrl="Scripts/MicrosoftAjax.js" publishTime="07/22/2011 07:26:00" />
    <file relUrl="Images/branding.jpg" publishTime="07/22/2011 07:26:00" />
    <file relUrl="Content/main.css" publishTime="07/22/2011 07:25:59" />
    <file relUrl="Content/Common/Icons/Suites_32/ORM.png" publishTime="07/22/2011 07:25:59" />
    <file relUrl="Scripts/tiny_mce/plugins/emotions/img/smiley-foot-in-mouth.gif" publishTime="07/22/2011 07:26:00" />
    <file relUrl="Scripts/tiny_mce/plugins/paste/js/pasteword.js" publishTime="07/22/2011 07:26:02" />
    <file relUrl="Scripts/tiny_mce/themes/advanced/source_editor.htm" publishTime="07/22/2011 07:26:02" />
    <file relUrl="Content/Common/Icons/Suites_32/SL.png" publishTime="07/22/2011 07:25:59" />
    <file relUrl="bin/Microsoft.ReportViewer.WebForms.dll" publishTime="07/22/2011 07:25:54" />
    <file relUrl="Content/font/Cicle_Fina_Italic-webfont.eot" publishTime="07/22/2011 07:25:59" />
    <file relUrl="Content/Windows7/sprite.png" publishTime="07/22/2011 07:25:59" />
    <file relUrl="Scripts/tiny_mce/plugins/preview/editor_plugin_src.js" publishTime="07/22/2011 07:26:02" />
    <file relUrl="Scripts/tiny_mce/plugins/insertdatetime/editor_plugin.js" publishTime="07/22/2011 07:26:01" />
    <file relUrl="Scripts/tiny_mce/plugins/xhtmlxtras/langs/en_dlg.js" publishTime="07/22/2011 07:26:02" />
    <file relUrl="Web.config" publishTime="08/10/2011 08:42:20" />
    <file relUrl="Images/Big_pdf.png" publishTime="07/22/2011 07:26:00" />
    <file relUrl="Scripts/MicrosoftMvcValidation.debug.js" publishTime="07/22/2011 07:26:00" />
    <file relUrl="Views/Proposal/AdminReviewerProposalDetails.ascx" publishTime="08/05/2011 07:35:13" />
    <file relUrl="Content/Common/Icons/Suites/sitefinity.png" publishTime="07/22/2011 07:25:59" />
    <file relUrl="Views/Proposal/ReviewerDetails.aspx" publishTime="07/22/2011 07:26:03" />
    <file relUrl="Scripts/tiny_mce/plugins/xhtmlxtras/js/abbr.js" publishTime="07/22/2011 07:26:02" />
    <file relUrl="Scripts/tiny_mce/themes/simple/skins/o2k7/content.css" publishTime="07/22/2011 07:26:02" />
    <file relUrl="Scripts/tiny_mce/plugins/media/img/flash.gif" publishTime="07/22/2011 07:26:01" />
    <file relUrl="Scripts/tiny_mce/plugins/media/editor_plugin.js" publishTime="07/22/2011 07:26:01" />
    <file relUrl="Scripts/tiny_mce/utils/validate.js" publishTime="07/22/2011 07:26:03" />
    <file relUrl="Images/Cancel.png" publishTime="07/22/2011 07:26:00" />
    <file relUrl="Scripts/tiny_mce/themes/advanced/skins/default/img/menu_arrow.gif" publishTime="07/22/2011 07:26:02" />
    <file relUrl="Scripts/tiny_mce/plugins/spellchecker/img/wline.gif" publishTime="07/22/2011 07:26:02" />
    <file relUrl="Views/Report/Launch.aspx" publishTime="07/22/2011 07:26:03" />
    <file relUrl="Views/EmailsForCall/SendCall.aspx" publishTime="07/22/2011 07:26:03" />
    <file relUrl="Views/Proposal/Confirmation.aspx" publishTime="07/22/2011 07:26:03" />
    <file relUrl="Content/NPOITemplate.xls" publishTime="07/22/2011 07:25:59" />
    <file relUrl="Content/Common/Icons/Suites_32/Test.png" publishTime="07/22/2011 07:25:59" />
    <file relUrl="Content/anytimec.css" publishTime="07/22/2011 07:25:59" />
    <file relUrl="Views/Public/LogOn.aspx" publishTime="07/22/2011 07:26:03" />
    <file relUrl="Content/Common/Icons/Suites/ajax.png" publishTime="07/22/2011 07:25:59" />
    <file relUrl="Scripts/tiny_mce/plugins/emotions/img/smiley-cry.gif" publishTime="07/22/2011 07:26:00" />
    <file relUrl="Views/Proposal/AdminDetails.aspx" publishTime="07/22/2011 07:26:03" />
    <file relUrl="Views/Shared/PublicSite.Master" publishTime="07/22/2011 07:26:03" />
    <file relUrl="Images/ajax-loader.gif" publishTime="07/22/2011 07:26:00" />
    <file relUrl="Scripts/tiny_mce/plugins/fullscreen/editor_plugin_src.js" publishTime="07/22/2011 07:26:01" />
    <file relUrl="bin/NPOI.xml" publishTime="07/22/2011 07:25:55" />
    <file relUrl="Scripts/tiny_mce/plugins/advlink/js/advlink.js" publishTime="07/22/2011 07:26:00" />
    <file relUrl="Content/images/ui-icons_f9bd01_256x240.png" publishTime="07/22/2011 07:25:59" />
    <file relUrl="Scripts/tiny_mce/plugins/emotions/img/smiley-embarassed.gif" publishTime="07/22/2011 07:26:00" />
    <file relUrl="Content/Common/Icons/Sl/Docking.gif" publishTime="07/22/2011 07:25:59" />
    <file relUrl="Content/Common/validation-error-message.png" publishTime="07/22/2011 07:25:59" />
    <file relUrl="Scripts/tiny_mce/themes/advanced/skins/o2k7/dialog.css" publishTime="07/22/2011 07:26:02" />
    <file relUrl="Views/Investigator/Create.aspx" publishTime="07/22/2011 07:26:03" />
    <file relUrl="Content/images/ui-icons_cd0a0a_256x240.png" publishTime="07/22/2011 07:25:59" />
    <file relUrl="Scripts/tiny_mce/plugins/advimage/img/sample.gif" publishTime="07/22/2011 07:26:00" />
    <file relUrl="Scripts/tiny_mce/plugins/pagebreak/editor_plugin.js" publishTime="07/22/2011 07:26:02" />
    <file relUrl="Scripts/tiny_mce/plugins/media/img/quicktime.gif" publishTime="07/22/2011 07:26:02" />
    <file relUrl="Scripts/tiny_mce/plugins/advimage/js/image.js" publishTime="07/22/2011 07:26:00" />
    <file relUrl="bin/NPOI.DDF.xml" publishTime="07/22/2011 07:25:55" />
    <file relUrl="Scripts/tiny_mce/plugins/advimage/editor_plugin.js" publishTime="07/22/2011 07:26:00" />
    <file relUrl="bin/Recaptcha.dll" publishTime="07/22/2011 07:25:55" />
    <file relUrl="Scripts/tiny_mce/themes/advanced/js/anchor.js" publishTime="07/22/2011 07:26:02" />
    <file relUrl="Content/font/Cicle_Gordita-webfont.eot" publishTime="07/22/2011 07:25:59" />
  </publishProfile>
</publishData>